{
    "2210.13451": {
        "title": "Superconducting Microsphere Magnetically Levitated in an Anharmonic Potential with Integrated Magnetic Readout",
        "authors": [
            "Martí Gutierrez Latorre",
            "Gerard Higgins",
            "Achintya Paradkar",
            "T. Bauch",
            "W. Wieczorek"
        ],
        "submission_date": "2022",
        "SemanticScholarId": "dd9b26cd8d3bf1d87fe693303022cf92194e1b12"
    },
    "2209.15326": {
        "title": "Simultaneous ground-state cooling of two mechanical modes of a levitated nanoparticle",
        "authors": [
            "J. Piotrowski",
            "Dominik Windey",
            "Jayadev Vijayan",
            "C. Gonzalez-Ballestero",
            "Andrés de los Ríos Sommer",
            "N. Meyer",
            "R. Quidant",
            "O. Romero-Isart",
            "R. Reimann",
            "L. Novotný"
        ],
        "submission_date": "2022",
        "SemanticScholarId": "bfb1bc8ebb046a3906593e1ab4ca93bade1a8698"
    },
    "2207.03641": {
        "title": "On-demand assembly of optically-levitated nanoparticle arrays in vacuum",
        "authors": [
            "Jiangwei Yan",
            "Xudong Yu",
            "Z. Han",
            "Tongcang Li",
            "Jing Zhang"
        ],
        "submission_date": "2022",
        "SemanticScholarId": "e2248001db5001a84bfe7f058edd63e07999e007"
    },
    "2205.00902": {
        "title": "Optical cold damping of neutral nanoparticles near the ground state in an optical lattice.",
        "authors": [
            "Mitsuyoshi Kamba",
            "Ryoga Shimizu",
            "Kiyotaka Aikawa"
        ],
        "submission_date": "2022",
        "SemanticScholarId": "9cfd85fdd34159a114b94ab7d06ebe3931f0922d"
    },
    "2203.04198": {
        "title": "Tunable light-induced dipole-dipole interaction between optically levitated nanoparticles",
        "authors": [
            "J. Rieser",
            "M. A. Ciampini",
            "H. Rudolph",
            "N. Kiesel",
            "K. Hornberger",
            "B. Stickler",
            "M. Aspelmeyer",
            "Uroš Delić"
        ],
        "submission_date": "2022",
        "SemanticScholarId": "f04293fe9c35160da6aee3b6382c8ad7a4d0dffb"
    },
    "2112.11383": {
        "title": "Two-dimensional quantum motion of a levitated nanosphere",
        "authors": [
            "A. Ranfagni",
            "K. Børkje",
            "F. Marino",
            "F. Marin"
        ],
        "submission_date": "2021",
        "SemanticScholarId": "973caafb1f3e30ad7494912bb0d2b626629e33e2"
    },
    "2111.05215": {
        "title": "Levitodynamics: Levitation and control of microscopic objects in vacuum",
        "authors": [
            "C. Gonzalez-Ballestero",
            "M. Aspelmeyer",
            "L. Novotny",
            "R. Quidant",
            "O. Romero-Isart"
        ],
        "submission_date": "2021",
        "SemanticScholarId": "aeeaccb2a4eb30582a5adf52d5427e34bd7fa334"
    },
    "2109.15071": {
        "title": "A Chip-Based Superconducting Magnetic Trap for Levitating Superconducting Microparticles",
        "authors": [
            "Martí Gutierrez Latorre",
            "Achintya Paradkar",
            "David Hambraeus",
            "Gerard Higgins",
            "W. Wieczorek"
        ],
        "submission_date": "2021",
        "SemanticScholarId": "77d3ea9caf90c32ada5f1a5da2615296b19f8ad8"
    },
    "2109.10316": {
        "title": "Direct and Clean Loading of Nanoparticles into Optical Traps at Millibar Pressures",
        "authors": [
            "M. Nikkhou",
            "Yanhui Hu",
            "James A. Sabin",
            "J. Millen"
        ],
        "submission_date": "2021",
        "SemanticScholarId": "e1b5e76d0f79c3cdcb8dc20352c9d609f8e10c84"
    },
    "2103.03853": {
        "title": "Quantum control of a nanoparticle optically levitated in cryogenic free space",
        "authors": [
            "L. Novotný",
            "F. Tebbenjohanns",
            "M. L. Mattana",
            "M. Rossi",
            "M. Frimmer"
        ],
        "submission_date": "2021",
        "SemanticScholarId": "b032a9269533bb844a2b8838e72f95fb3b95d370"
    },
    "2012.15188": {
        "title": "Real-time optimal quantum control of mechanical motion at room temperature",
        "authors": [
            "Lorenzo Magrini",
            "Philipp Rosenzweig",
            "Constanze Bach",
            "A. Deutschmann‐Olek",
            "Sebastian G. Hofer",
            "Sungkun Hong",
            "N. Kiesel",
            "A. Kugi",
            "M. Aspelmeyer"
        ],
        "submission_date": "2020",
        "SemanticScholarId": "68105eb6e6cf01285572d2803ee527f3f73c264e"
    },
    "2012.15265": {
        "title": "Vectorial polaritons in the quantum motion of a levitated nanosphere",
        "authors": [
            "A. Ranfagni",
            "P. Vezio",
            "M. Calamai",
            "A. Chowdhury",
            "F. Marino",
            "F. Marin"
        ],
        "submission_date": "2020",
        "SemanticScholarId": "953b6798ac875909bc5003e2cc4b6369f3e9807e"
    },
    "2005.10201": {
        "title": "Strong optomechanical coupling at room temperature by coherent scattering",
        "authors": [
            "Andrés de los Ríos Sommer",
            "N. Meyer",
            "R. Quidant"
        ],
        "submission_date": "2020",
        "SemanticScholarId": "591fd8db91f7ad03fa64cba6b515f40b20269dee"
    },
    "2005.05486": {
        "title": "Extending vacuum trapping to absorbing objects with hybrid Paul-optical traps.",
        "authors": [
            "Gerard P. Conangla",
            "R. Rica",
            "R. Quidant"
        ],
        "submission_date": "2020",
        "SemanticScholarId": "542abd2a5bc6209232c1ae5f0147c15944b604c4"
    },
    "2002.07585": {
        "title": "High-Sensitivity Accelerometry with a Feedback-Cooled Magnetically Levitated Microsphere",
        "authors": [
            "C. Lewandowski",
            "T. Knowles",
            "Z. Etienne",
            "B. D’Urso"
        ],
        "submission_date": "2020",
        "SemanticScholarId": "5f3e47c72c8bbd7394756808abcdee7c3a74f721"
    },
    "1912.12252": {
        "title": "Ultralow Mechanical Damping with Meissner-Levitated Ferromagnetic Microparticles",
        "authors": [
            "A. Vinante",
            "A. Vinante",
            "P. Falferi",
            "Giulio Gasbarri",
            "Ashley Setter",
            "C. Timberlake",
            "H. Ulbricht"
        ],
        "submission_date": "2019",
        "SemanticScholarId": "28cbda736633e11a8bead47d3fc907a9fde0b202"
    },
    "1912.10397": {
        "title": "Single-Spin Magnetomechanics with Levitated Micromagnets.",
        "authors": [
            "J. Gieseler",
            "A. Kabcenell",
            "E. Rosenfeld",
            "J. Schaefer",
            "A. Safira",
            "M. Schuetz",
            "C. Gonzalez-Ballestero",
            "C. C. Rusconi",
            "O. Romero-Isart",
            "M. Lukin"
        ],
        "submission_date": "2019",
        "SemanticScholarId": "65870b4b1418fdc2ad16dab1bad5dcf3771c73dc"
    },
    "1911.04406": {
        "title": "Cooling of a levitated nanoparticle to the motional quantum ground state",
        "authors": [
            "Uroš Delić",
            "Manuel Reisenbauer",
            "Kahan Dare",
            "David Grass",
            "V. Vuletić",
            "N. Kiesel",
            "M. Aspelmeyer"
        ],
        "submission_date": "2019",
        "SemanticScholarId": "52a6656fe01443c37752d61cd5aa0e9bdd0d10cc"
    },
    "1910.07078": {
        "title": "Acceleration sensing with magnetically levitated oscillators above a superconductor",
        "authors": [
            "C. Timberlake",
            "Giulio Gasbarri",
            "A. Vinante",
            "Ashley Setter",
            "H. Ulbricht"
        ],
        "submission_date": "2019",
        "SemanticScholarId": "a8c233651b7f951bf75604f71fc050a15843ee09"
    },
    "1907.12838": {
        "title": "Optimal position detection of a dipolar scatterer in a focused field",
        "authors": [
            "F. Tebbenjohanns",
            "M. Frimmer",
            "L. Novotný"
        ],
        "submission_date": "2019",
        "SemanticScholarId": "464e3de690eb026a2f274e9a9bb4a069c7ac908f"
    },
    "1907.08198": {
        "title": "Optomechanics with levitated particles",
        "authors": [
            "J. Millen",
            "T. S. Monteiro",
            "R. Pettit",
            "Nick Vamivakas"
        ],
        "submission_date": "2019",
        "SemanticScholarId": "0ad78f7caea5277996149283d4f43bc1a67158ff"
    },
    "1905.11509": {
        "title": "Spin-cooling of the motion of a trapped diamond",
        "authors": [
            "T. Delord",
            "P. Huillery",
            "L. Nicolas",
            "G. H'etet"
        ],
        "submission_date": "2019",
        "SemanticScholarId": "5b5d685473995b50281e39c1306bacc22809da21"
    },
    "1902.01282": {
        "title": "Theory for cavity cooling of levitated nanoparticles via coherent scattering: Master equation approach",
        "authors": [
            "C. Gonzalez-Ballestero",
            "C. Gonzalez-Ballestero",
            "P. Maurer",
            "P. Maurer",
            "Dominik Windey",
            "L. Novotný",
            "R. Reimann",
            "O. Romero-Isart",
            "O. Romero-Isart"
        ],
        "submission_date": "2019",
        "SemanticScholarId": "2bc066f4f6da1f5e2999ce1b91a0215d009c8fbf"
    },
    "1810.08748": {
        "title": "Dynamics of a Ferromagnetic Particle Levitated over a Superconductor",
        "authors": [
            "Tao Wang",
            "S. Lourette",
            "S. R. Kelley",
            "M. Kayci",
            "Y. Band",
            "D. F. Kimball",
            "A. Sushkov",
            "D. Budker"
        ],
        "submission_date": "2018",
        "SemanticScholarId": "78e1f27058a68d3be6269fd2623795c1b287e78e"
    },
    "1810.00163": {
        "title": "Prethermalization and Nonreciprocal Phonon Transport in a Levitated Optomechanical Array",
        "authors": [
            "Shengyan Liu",
            "Z. Yin",
            "Tongcang Li"
        ],
        "submission_date": "2018",
        "SemanticScholarId": "fb41889a684938e05538961f1b53950facb35d8d"
    },
    "1804.09275": {
        "title": "Ultrastrong coupling regimes of light-matter interaction",
        "authors": [
            "P. Forn-D'iaz",
            "L. Lamata",
            "E. Rico",
            "J. Kono",
            "E. Solano"
        ],
        "submission_date": "2018",
        "SemanticScholarId": "b7d1419f1fa57ed5ae05ad2e938b541a86da5de8"
    },
    "1804.06676": {
        "title": "Near-field coupling of a levitated nanoparticle to a photonic crystal cavity",
        "authors": [
            "Lorenzo Magrini",
            "R. Norte",
            "R. Riedinger",
            "I. Marinković",
            "David Grass",
            "Uroš Delić",
            "S. Gröblacher",
            "Sungkun Hong",
            "M. Aspelmeyer"
        ],
        "submission_date": "2018",
        "SemanticScholarId": "75b516a8878374f3f96a1c5244642a27dfb4fbfa"
    },
    "1803.05527": {
        "title": "Motion Control and Optical Interrogation of a Levitating Single Nitrogen Vacancy in Vacuum.",
        "authors": [
            "Gerard P. Conangla",
            "A. Schell",
            "R. Rica",
            "R. Quidant"
        ],
        "submission_date": "2018",
        "SemanticScholarId": "be30e04c02de7e21d4d7058cebffe3668be4d56f"
    },
    "1603.09393": {
        "title": "Optical trapping and control of nanoparticles inside evacuated hollow core photonic crystal fibers",
        "authors": [
            "David Grass",
            "J. Fesel",
            "Sebastian G. Hofer",
            "N. Kiesel",
            "M. Aspelmeyer"
        ],
        "submission_date": "2016",
        "SemanticScholarId": "1f95e89b25154a6cbc5b4494673717a09c27f021"
    },
    "1603.03420": {
        "title": "Direct Measurement of Photon Recoil from a Levitated Nanoparticle.",
        "authors": [
            "V. Jain",
            "Jan Gieseler",
            "Clemens Moritz",
            "C. Dellago",
            "R. Quidant",
            "L. Novotný"
        ],
        "submission_date": "2016",
        "SemanticScholarId": "ec34306020a1828c32f380053143a604f278a4bf"
    },
    "1511.08482": {
        "title": "Nonlinear Dynamics and Strong Cavity Cooling of Levitated Nanoparticles.",
        "authors": [
            "P. Z. Fonseca",
            "E. Aranas",
            "J. Millen",
            "T. S. Monteiro",
            "P. Barker"
        ],
        "submission_date": "2015",
        "SemanticScholarId": "91f9afe3641280f0b409c6c56f7cdaef05326c77"
    },
    "1510.05368": {
        "title": "A quantum optomechanical interface beyond the resolved sideband limit",
        "authors": [
            "J. Bennett",
            "K. Khosla",
            "L. Madsen",
            "M. Vanner",
            "H. Rubinsztein-Dunlop",
            "W. Bowen"
        ],
        "submission_date": "2015",
        "SemanticScholarId": "8370f2a38ad0893779564cd866eadb9ce5448fc7"
    },
    "1505.03363": {
        "title": "Near-field levitated quantum optomechanics with nanodiamonds",
        "authors": [
            "M. Juan",
            "G. Molina-Terriza",
            "T. Volz",
            "O. Romero-Isart"
        ],
        "submission_date": "2015",
        "SemanticScholarId": "40b266dcc496f3ae48e9c27352ee921b924a5bc5"
    },
    "1312.0500": {
        "title": "Near-field interferometry of a free-falling nanoparticle from a point-like source",
        "authors": [
            "J. Bateman",
            "S. Nimmrichter",
            "K. Hornberger",
            "H. Ulbricht"
        ],
        "submission_date": "2013",
        "SemanticScholarId": "5554fa9089594e1045ace470ea997dd97e01731b"
    },
    "1212.4691": {
        "title": "Cavity optomechanics of levitated nanodumbbells: nonequilibrium phases and self-assembly.",
        "authors": [
            "W. Lechner",
            "S. Habraken",
            "N. Kiesel",
            "M. Aspelmeyer",
            "P. Zoller"
        ],
        "submission_date": "2012",
        "SemanticScholarId": "79cd6f3272aabc4f1354e7e30af869e09317387c"
    },
    "1112.5609": {
        "title": "Quantum magnetomechanics with levitating superconducting microspheres.",
        "authors": [
            "O. Romero-Isart",
            "Lucas Clemente",
            "C. Navau",
            "Alvaro Sanchez",
            "J. Cirac"
        ],
        "submission_date": "2011",
        "SemanticScholarId": "edca48ee0ef8e4c1a03062e46bdb2fd3f398ce32"
    },
    "1102.4905": {
        "title": "Backward Pulling Force from a Forward Propagating Beam",
        "authors": [
            "Jun Chen",
            "J. Ng",
            "Zhifang Lin",
            "C. T. Chan"
        ],
        "submission_date": "2011",
        "SemanticScholarId": "49f5f11f9ef6b11f4623f31582e73ac93c28c0f9"
    },
    "1006.0261": {
        "title": "Short-range force detection using optically cooled levitated microspheres.",
        "authors": [
            "A. Geraci",
            "S. Papp",
            "J. Kitching"
        ],
        "submission_date": "2010",
        "SemanticScholarId": "cefd6f9121ec236bde953b54711d07180911928d"
    },
    "0912.1179": {
        "title": "Optical interface created by laser-cooled atoms trapped in the evanescent field surrounding an optical nanofiber.",
        "authors": [
            "E. Vetsch",
            "D. Reitz",
            "G. Sagué",
            "R. Schmidt",
            "S. Dawkins",
            "A. Rauschenbeutel"
        ],
        "submission_date": "2009",
        "SemanticScholarId": "7f94e282cc442844334eab732a5373d8b73899b5"
    },
    "0909.5090": {
        "title": "Bose-Einstein condensation in dark power-law laser traps",
        "authors": [
            "A. Jaouadi",
            "N. Gaaloul",
            "B. V. Lesegno",
            "M. Telmini",
            "L. Pruvost",
            "E. Charron"
        ],
        "submission_date": "2009",
        "SemanticScholarId": "9270b568572f5b54505234e3cac32305caac6b68"
    },
    "0901.4158": {
        "title": "High quality factor photonic crystal nanobeam cavities",
        "authors": [
            "P. Deotare",
            "M. Mccutcheon",
            "I. Frank",
            "M. Khan",
            "M. Lončar"
        ],
        "submission_date": "2009",
        "SemanticScholarId": "fb991a1e859a03813b19e1ebc49b427e805e1578"
    },
    "quant-ph/0407107": {
        "title": "Atom trap and waveguide using a two-color evanescent light field around a subwavelength-diameter optical fiber",
        "authors": [
            "F. Kien",
            "V. Balykin",
            "K. Hakuta"
        ],
        "submission_date": "2004",
        "SemanticScholarId": "0dd755d4ad130341ebdf4f85f3269724c2c708ae"
    },
    "physics/9902072": {
        "title": "Optical dipole traps for neutral atoms",
        "authors": [
            "R. Grimm",
            "M. Weidemuller",
            "Y. Ovchinnikov"
        ],
        "submission_date": "1999",
        "SemanticScholarId": "0e4a3aeb5f7d9cfd4d5a1717e51bd739de37e5d7"
    }
}