{
    "2301.03220": {
        "title": "Enabling AI-Generated Content (AIGC) Services in Wireless Edge Networks",
        "authors": [
            "Hongyang Du",
            "Zonghang Li",
            "D. Niyato",
            "Jiawen Kang",
            "Zehui Xiong",
            "X. Shen",
            "Dong In Kim"
        ],
        "submission_date": "2023",
        "SemanticScholarId": "8e3d28a46997f0b2f84192697b9167a763031156"
    },
    "2209.14147": {
        "title": "Mobile Edge Computing, Metaverse, 6G Wireless Communications, Artificial Intelligence, and Blockchain: Survey and Their Convergence",
        "authors": [
            "Yitong Wang",
            "Jun Zhao"
        ],
        "submission_date": "2022",
        "SemanticScholarId": "b7f05fb83421bdb2c2890ed146f232990a5c0dbb"
    },
    "2208.13501": {
        "title": "When Internet of Things Meets Metaverse: Convergence of Physical and Cyber Worlds",
        "authors": [
            "Kai Li",
            "Ying-Kai Cui",
            "Weicai Li",
            "Tiejun Lv",
            "Xinnan Yuan",
            "Shenghong Li",
            "W. Ni",
            "M. Simsek",
            "F. Dressler"
        ],
        "submission_date": "2022",
        "SemanticScholarId": "0d6ec3ac864952a4573f0a53641a3bec09cc5e0b"
    },
    "2208.05438": {
        "title": "Attention-Aware Resource Allocation and QoE Analysis for Metaverse xURLLC Services",
        "authors": [
            "Hongyang Du",
            "Jiazhen Liu",
            "Dusist Niyato",
            "Jiawen Kang",
            "Zehui Xiong",
            "Junshan Zhang",
            "Dong In Kim"
        ],
        "submission_date": "2022",
        "SemanticScholarId": "3c5002855de5f2771815275d712bdb7323c06b6c"
    },
    "2208.00369": {
        "title": "Exploring Attention-Aware Network Resource Allocation for Customized Metaverse Services",
        "authors": [
            "H. Du",
            "Jiacheng Wang",
            "Dusist Niyato",
            "Jiawen Kang",
            "Zehui Xiong",
            "X. Shen",
            "Dong In Kim"
        ],
        "submission_date": "2022",
        "SemanticScholarId": "0b52e44ef443742f47756321078a694adc47f616"
    },
    "2206.07384": {
        "title": "Blockchain-based Federated Learning for Industrial Metaverses: Incentive Scheme with Optimal AoI",
        "authors": [
            "Jiawen Kang",
            "Dongdong Ye",
            "Jiangtian Nie",
            "Jiang Xiao",
            "Xi Deng",
            "Siming Wang",
            "Zehui Xiong",
            "Rong Yu",
            "D. Niyato"
        ],
        "submission_date": "2022",
        "SemanticScholarId": "f8644322a6f2f83cb91773f84f43e86143a713a7"
    },
    "2204.06192": {
        "title": "6G-enabled Edge AI for Metaverse: Challenges, Methods, and Future Research Directions",
        "authors": [
            "Luyi Chang",
            "Zhe Zhang",
            "Pei Li",
            "Shan Xi",
            "Wei-Xiang Guo",
            "Yukang Shen",
            "Zehui Xiong",
            "Jiawen Kang",
            "D. Niyato",
            "Xiuquan Qiao",
            "Yi Wu"
        ],
        "submission_date": "2022",
        "SemanticScholarId": "9ef4fd981d652567bf5bd6e3b435808eb3c3317c"
    },
    "2203.05471": {
        "title": "A Full Dive Into Realizing the Edge-Enabled Metaverse: Visions, Enabling Technologies, and Challenges",
        "authors": [
            "Minrui Xu",
            "Wei Chong Ng",
            "Wei Yang Bryan Lim",
            "Jiawen Kang",
            "Zehui Xiong",
            "D. Niyato",
            "Qiang Yang",
            "X. Shen",
            "Chunyan Miao"
        ],
        "submission_date": "2022",
        "SemanticScholarId": "4c397c32fe121f32445bb5ca90e3a8d07b9e785e"
    },
    "2202.01512": {
        "title": "Data Heterogeneity-Robust Federated Learning via Group Client Selection in Industrial IoT",
        "authors": [
            "Zonghang Li",
            "Yihong He",
            "Hongfang Yu",
            "Jiawen Kang",
            "Xiaoping Li",
            "Zenglin Xu",
            "Dusist Niyato"
        ],
        "submission_date": "2022",
        "SemanticScholarId": "5d4e2b2b5288d82581e2576edfa96c322e8002f0"
    },
    "2201.12976": {
        "title": "Heterogeneous Federated Learning via Grouped Sequential-to-Parallel Training",
        "authors": [
            "Shenglai Zeng",
            "Zonghang Li",
            "Hongfang Yu",
            "Yihong He",
            "Zenglin Xu",
            "D. Niyato",
            "Han Yu"
        ],
        "submission_date": "2022",
        "SemanticScholarId": "7b3eb68256902ccced71d19db72d4d5444b71758"
    },
    "2201.03201": {
        "title": "Fusing Blockchain and AI With Metaverse: A Survey",
        "authors": [
            "Qinglin Yang",
            "Yetong Zhao",
            "Huawei Huang",
            "Zehui Xiong",
            "Jiawen Kang",
            "Zibin Zheng"
        ],
        "submission_date": "2022",
        "SemanticScholarId": "8aa6119a85e28dc84024fc64764ffb687c52a6f3"
    },
    "2110.02221": {
        "title": "Securing Federated Learning: A Covert Communication-Based Approach",
        "authors": [
            "Yuan-ai Xie",
            "Jiawen Kang",
            "D. Niyato",
            "Nguyen Thi Thanh Van",
            "Nguyen Cong Luong",
            "Zhixin Liu",
            "Han Yu"
        ],
        "submission_date": "2021",
        "SemanticScholarId": "b334be9687a19c317bcb09df8919d9ef38dd3b1f"
    },
    "2106.05001": {
        "title": "No Fear of Heterogeneity: Classifier Calibration for Federated Learning with Non-IID Data",
        "authors": [
            "Romy Mi Luo",
            "Fei Chen",
            "Dapeng Hu",
            "Yifan Zhang",
            "Jian Liang",
            "Jiashi Feng"
        ],
        "submission_date": "2021",
        "SemanticScholarId": "9563e9578073447b68261eda55e7a6c4fb2af7c8"
    },
    "2008.07665": {
        "title": "Inverse Distance Aggregation for Federated Learning with Non-IID Data",
        "authors": [
            "Yousef Yeganeh",
            "Azade Farshad",
            "N. Navab",
            "Shadi Albarqouni"
        ],
        "submission_date": "2020",
        "SemanticScholarId": "bc9045ee4441e0df039ad5281e7654ba39283469"
    },
    "2004.00713": {
        "title": "Memory-Efficient Incremental Learning Through Feature Adaptation",
        "authors": [
            "Ahmet Iscen",
            "Jeffrey O. Zhang",
            "Svetlana Lazebnik",
            "C. Schmid"
        ],
        "submission_date": "2020",
        "SemanticScholarId": "7c907dbfecd870208249342951e49e1417621442"
    },
    "2003.00295": {
        "title": "Adaptive Federated Optimization",
        "authors": [
            "Sashank J. Reddi",
            "Zachary B. Charles",
            "M. Zaheer",
            "Zachary Garrett",
            "Keith Rush",
            "Jakub Konecný",
            "Sanjiv Kumar",
            "H. B. McMahan"
        ],
        "submission_date": "2020",
        "SemanticScholarId": "47c528344fedb6cb67a38e43d095b41c34715330"
    },
    "2001.04756": {
        "title": "Adaptive Gradient Sparsification for Efficient Federated Learning: An Online Learning Approach",
        "authors": [
            "Pengchao Han",
            "Shiqiang Wang",
            "K. Leung"
        ],
        "submission_date": "2020",
        "SemanticScholarId": "da93d65ce761de78992989dae8d2af8aeeada54d"
    },
    "1912.04977": {
        "title": "Advances and Open Problems in Federated Learning",
        "authors": [
            "P. Kairouz",
            "H. B. McMahan",
            "Brendan Avent",
            "A. Bellet",
            "M. Bennis",
            "A. Bhagoji",
            "Keith Bonawitz",
            "Zachary B. Charles",
            "Graham Cormode",
            "Rachel Cummings",
            "Rafael G. L. D'Oliveira",
            "S. E. Rouayheb",
            "David Evans",
            "Josh Gardner",
            "Zachary Garrett",
            "Adrià Gascón",
            "Badih Ghazi",
            "Phillip B. Gibbons",
            "M. Gruteser",
            "Zaïd Harchaoui",
            "Chaoyang He",
            "Lie He",
            "Zhouyuan Huo",
            "Ben Hutchinson",
            "Justin Hsu",
            "Martin Jaggi",
            "T. Javidi",
            "Gauri Joshi",
            "M. Khodak",
            "Jakub Konecný",
            "A. Korolova",
            "F. Koushanfar",
            "Oluwasanmi Koyejo",
            "Tancrède Lepoint",
            "Yang Liu",
            "Prateek Mittal",
            "M. Mohri",
            "R. Nock",
            "A. Özgür",
            "R. Pagh",
            "Mariana Raykova",
            "Hang Qi",
            "Daniel Ramage",
            "R. Raskar",
            "D. Song",
            "Weikang Song",
            "Sebastian U. Stich",
            "Ziteng Sun",
            "A. Suresh",
            "Florian Tramèr",
            "Praneeth Vepakomma",
            "Jianyu Wang",
            "Li Xiong",
            "Zheng Xu",
            "Qiang Yang",
            "Felix X. Yu",
            "Han Yu",
            "Sen Zhao"
        ],
        "submission_date": "2019",
        "SemanticScholarId": "07912741c6c96e6ad5b2c2d6c6c3b2de5c8a271b"
    },
    "1912.01100": {
        "title": "Latent Replay for Real-Time Continual Learning",
        "authors": [
            "Lorenzo Pellegrini",
            "G. Graffieti",
            "Vincenzo Lomonaco",
            "D. Maltoni"
        ],
        "submission_date": "2019",
        "SemanticScholarId": "1770eb53d3529979d3446b55b11c16e181aa469e"
    },
    "1907.01132": {
        "title": "Astraea: Self-Balancing Federated Learning for Improving Classification Accuracy of Mobile Deep Learning Applications",
        "authors": [
            "Moming Duan"
        ],
        "submission_date": "2019",
        "SemanticScholarId": "1aa245db626691d092f263210be486cb6d8023a5"
    },
    "1812.06127": {
        "title": "Federated Optimization in Heterogeneous Networks",
        "authors": [
            "Anit Kumar Sahu",
            "Tian Li",
            "Maziar Sanjabi",
            "M. Zaheer",
            "Ameet Talwalkar",
            "Virginia Smith"
        ],
        "submission_date": "2018",
        "SemanticScholarId": "1284ed4bf6a043ecf8cebca09e4811f1e3b83b65"
    },
    "1812.01097": {
        "title": "LEAF: A Benchmark for Federated Settings",
        "authors": [
            "S. Caldas",
            "Peter Wu",
            "Tian Li",
            "Jakub Konecný",
            "H. B. McMahan",
            "Virginia Smith",
            "Ameet Talwalkar"
        ],
        "submission_date": "2018",
        "SemanticScholarId": "8dcbcaaf337d7bd22e580f1bb7a795ed4bb604fd"
    },
    "1811.11479": {
        "title": "Communication-Efficient On-Device Machine Learning: Federated Distillation and Augmentation under Non-IID Private Data",
        "authors": [
            "Eunjeong Jeong",
            "Seungeun Oh",
            "Hyesung Kim",
            "Jihong Park",
            "M. Bennis",
            "Seong-Lyun Kim"
        ],
        "submission_date": "2018",
        "SemanticScholarId": "015562837d3bf7fbdfbaccb43eadc6981ee5e35e"
    },
    "1806.00582": {
        "title": "Federated Learning with Non-IID Data",
        "authors": [
            "Yue Zhao",
            "Meng Li",
            "Liangzhen Lai",
            "Naveen Suda",
            "Damon Civin",
            "V. Chandra"
        ],
        "submission_date": "2018",
        "SemanticScholarId": "5cfc112c932e38df95a0ba35009688735d1a386b"
    },
    "1802.02871": {
        "title": "Online Learning: A Comprehensive Survey",
        "authors": [
            "S. Hoi",
            "Doyen Sahoo",
            "Jing Lu",
            "P. Zhao"
        ],
        "submission_date": "2018",
        "SemanticScholarId": "b3d5115c17318675f8c94e13a2dc1d8b568e633a"
    },
    "1712.01887": {
        "title": "Deep Gradient Compression: Reducing the Communication Bandwidth for Distributed Training",
        "authors": [
            "Yujun Lin",
            "Song Han",
            "Huizi Mao",
            "Yu Wang",
            "W. Dally"
        ],
        "submission_date": "2017",
        "SemanticScholarId": "92495abbac86394cb759bec15a763dbf49a8e590"
    },
    "1708.06519": {
        "title": "Learning Efficient Convolutional Networks through Network Slimming",
        "authors": [
            "Zhuang Liu",
            "Jianguo Li",
            "Zhiqiang Shen",
            "Gao Huang",
            "Shoumeng Yan",
            "Changshui Zhang"
        ],
        "submission_date": "2017",
        "SemanticScholarId": "90a16f34d109b63d95ab4da2d491cbe3a1c8b656"
    },
    "1611.07725": {
        "title": "iCaRL: Incremental Classifier and Representation Learning",
        "authors": [
            "Sylvestre-Alvise Rebuffi",
            "Alexander Kolesnikov",
            "G. Sperl",
            "Christoph H. Lampert"
        ],
        "submission_date": "2016",
        "SemanticScholarId": "1703631a938b397ba7e858161ce16448f6046d6f"
    },
    "1612.01543": {
        "title": "Towards the Limit of Network Quantization",
        "authors": [
            "Yoojin Choi",
            "Mostafa El-Khamy",
            "Jungwon Lee"
        ],
        "submission_date": "2016",
        "SemanticScholarId": "6d749712ef4f02a87f4e362058469a1da46c8bcc"
    },
    "1608.03665": {
        "title": "Learning Structured Sparsity in Deep Neural Networks",
        "authors": [
            "W. Wen",
            "Chunpeng Wu",
            "Yandan Wang",
            "Yiran Chen",
            "Hai Helen Li"
        ],
        "submission_date": "2016",
        "SemanticScholarId": "7601b995303f953955004db7b9b8b206c0e02ff8"
    },
    "1602.05629": {
        "title": "Communication-Efficient Learning of Deep Networks from Decentralized Data",
        "authors": [
            "H. B. McMahan",
            "Eider Moore",
            "Daniel Ramage",
            "S. Hampson",
            "B. A. Y. Arcas"
        ],
        "submission_date": "2016",
        "SemanticScholarId": "d1dbf643447405984eeef098b1b320dee0b3b8a7"
    },
    "1511.00363": {
        "title": "BinaryConnect: Training Deep Neural Networks with binary weights during propagations",
        "authors": [
            "Matthieu Courbariaux",
            "Yoshua Bengio",
            "J. David"
        ],
        "submission_date": "2015",
        "SemanticScholarId": "a5733ff08daff727af834345b9cfff1d0aa109ec"
    },
    "1507.06149": {
        "title": "Data-free Parameter Pruning for Deep Neural Networks",
        "authors": [
            "Suraj Srinivas",
            "R. Venkatesh Babu"
        ],
        "submission_date": "2015",
        "SemanticScholarId": "b0bd441a0cc04cdd0d0e469fe4c5184ee148a97d"
    },
    "1506.02626": {
        "title": "Learning both Weights and Connections for Efficient Neural Network",
        "authors": [
            "Song Han",
            "Jeff Pool",
            "J. Tran",
            "W. Dally"
        ],
        "submission_date": "2015",
        "SemanticScholarId": "1ff9a37d766e3a4f39757f5e1b235a42dacf18ff"
    },
    "1412.6115": {
        "title": "Compressing Deep Convolutional Networks using Vector Quantization",
        "authors": [
            "Yunchao Gong",
            "L. Liu",
            "Ming Yang",
            "Lubomir D. Bourdev"
        ],
        "submission_date": "2014",
        "SemanticScholarId": "e7bf9803705f2eb608db1e59e5c7636a3f171916"
    },
    "1206.5538": {
        "title": "Representation Learning: A Review and New Perspectives",
        "authors": [
            "Yoshua Bengio",
            "Aaron C. Courville",
            "Pascal Vincent"
        ],
        "submission_date": "2012",
        "SemanticScholarId": "184ac0766262312ba76bbdece4e7ffad0aa8180b"
    }
}