{
    "partition": "test",
    "groundtruth": {
        "LiaoYuLiu2019": "1904.00186",
        "carstensen2021direct": "2105.01505",
        "CanDusMadStaVoh2020": "2008.04140"
    },
    "prediction": {
        "LiaoYuLiu2019": [
            "1904.00186",
            "1904.07903",
            "1610.04450",
            "1204.4119",
            "1808.08148"
        ],
        "carstensen2021direct": [
            "2105.01505",
            "1808.08148",
            "2008.04140",
            "1801.02561",
            "1904.07903"
        ],
        "CanDusMadStaVoh2020": [
            "2008.04140",
            "1808.08148",
            "1904.07903",
            "1602.08961",
            "1801.02561"
        ]
    }
}