{
    "2201.06337": {
        "title": "PoVRPoint: Authoring Presentations in Mobile Virtual Reality",
        "authors": [
            "Verena Biener",
            "Travis Gesslein",
            "D. Schneider",
            "Felix Kawala",
            "Alexander Otte",
            "P. Kristensson",
            "M. Pahud",
            "E. Ofek",
            "Cuauhtli Campos",
            "Matjavz Kljun",
            "Klen vCopivc Pucihar",
            "Jens Grubert"
        ],
        "submission_date": "2022",
        "SemanticScholarId": "25f66107c5105a02c54895988e0d85be6441c246"
    }
}