{
    "2207.12885": {
        "title": "All-electrical switching of a topological non-collinear antiferromagnet at room temperature",
        "authors": [
            "Yongcheng Deng",
            "Xionghua Liu",
            "Yiyuan Chen",
            "Z. Du",
            "Nai Jiang",
            "Chao Shen",
            "Enze Zhang",
            "Hou-zhi Zheng",
            "Hai-Zhou Lu",
            "Kaiyou Wang"
        ],
        "submission_date": "2022",
        "SemanticScholarId": "250cc3eab0e809e1ba8c7725c8639abeaeac1942"
    },
    "2012.13502": {
        "title": "Skyrmion control of Majorana states in planar Josephson junctions",
        "authors": [
            "N. Mohanta",
            "S. Okamoto",
            "E. Dagotto"
        ],
        "submission_date": "2020",
        "SemanticScholarId": "1370538302badb498ceb3266faa5aaa295fe12de"
    },
    "2008.05303": {
        "title": "Anomalous spin Hall and inverse spin Hall effects in magnetic systems",
        "authors": [
            "X. R. Wang"
        ],
        "submission_date": "2020",
        "SemanticScholarId": "fea27802c8ac2e88b1cd44fdf8fcbbd1c2ae81bc"
    },
    "2006.08912": {
        "title": "Electrical manipulation of a topological antiferromagnetic state",
        "authors": [
            "Hanshen Tsai",
            "T. Higo",
            "K. Kondou",
            "T. Nomoto",
            "A. Sakai",
            "A. Kobayashi",
            "T. Nakano",
            "K. Yakushiji",
            "R. Arita",
            "S. Miwa",
            "Y. Otani",
            "S. Nakatsuji"
        ],
        "submission_date": "2020",
        "SemanticScholarId": "0223ee6893fe819474d3c0cd4915925ac0cd568c"
    },
    "1911.00943": {
        "title": "Magnetic Damping Modulation in IrMn_{3}/Ni_{80}Fe_{20} via the Magnetic Spin Hall Effect.",
        "authors": [
            "J. Holanda",
            "H. Sağlam",
            "Vedat Karakaş",
            "Zhizhi Zang",
            "Yi Li",
            "R. Divan",
            "Yuzi Liu",
            "O. Ozatay",
            "V. Novosad",
            "J. Pearson",
            "A. Hoffmann"
        ],
        "submission_date": "2019",
        "SemanticScholarId": "b0acc2d1512b2e553974ccdda29bce5f367316d0"
    },
    "1910.07136": {
        "title": "Spin-wave frequency division multiplexing in an yttrium iron garnet microstripe magnetized by inhomogeneous field",
        "authors": [
            "Zhizhi Zhang",
            "Zhizhi Zhang",
            "M. Vogel",
            "J. Holanda",
            "M. Jungfleisch",
            "Changjiang Liu",
            "Yi Li",
            "Yi Li",
            "J. Pearson",
            "R. Divan",
            "Wei Zhang",
            "Axel Hoffmann",
            "Axel Hoffmann",
            "Y. Nie",
            "V. Novosad"
        ],
        "submission_date": "2019",
        "SemanticScholarId": "9fe711eab9fff7c3308972dbbe70f1837db0b513"
    },
    "1905.07962": {
        "title": "Topology analysis for anomalous Hall effect in the noncollinear antiferromagnetic states of \nMn3AN\n \n(A=Ni, Cu, Zn, Ga, Ge, Pd, In, Sn, Ir, Pt)",
        "authors": [
            "Vu Thi Ngoc Huyen",
            "Michi-To Suzuki",
            "K. Yamauchi",
            "T. Oguchi"
        ],
        "submission_date": "2019",
        "SemanticScholarId": "08c37c8c8d1260dd2577b8bd018c7a4022fd7c6c"
    },
    "1810.11599": {
        "title": "Anomalous Hall effect in thin films of the Weyl antiferromagnet Mn3Sn",
        "authors": [
            "T. Higo",
            "D. Qu",
            "Yufan Li",
            "C. Chien",
            "Y. Otani",
            "S. Nakatsuji",
            "S. Nakatsuji"
        ],
        "submission_date": "2018",
        "SemanticScholarId": "e650cbccf7f39dc9e696811008dbcef826527bcd"
    },
    "1802.04448": {
        "title": "Inducing ferromagnetism and Kondo effect in platinum by paramagnetic ionic gating",
        "authors": [
            "L. Liang",
            "Qihong Chen",
            "Jianming Lu",
            "Wytse Talsma",
            "J. Shan",
            "G. Blake",
            "T. Palstra",
            "Jianting Ye"
        ],
        "submission_date": "2018",
        "SemanticScholarId": "451fcbc16e91a9ea4124d0eade0036ab7ff094a9"
    },
    "1702.00295": {
        "title": "Spin-Polarized Current in Noncollinear Antiferromagnets.",
        "authors": [
            "J. Železný",
            "Yang Zhang",
            "C. Felser",
            "Binghai Yan"
        ],
        "submission_date": "2017",
        "SemanticScholarId": "c55f1effbc92305d8cb8a8f9129f2d224710af6b"
    },
    "1504.07929": {
        "title": "Role of transparency of platinum–ferromagnet interfaces in determining the intrinsic magnitude of the spin Hall effect",
        "authors": [
            "Weifeng Zhang",
            "W. Han",
            "Xin Jiang",
            "See-Hun Yang",
            "Stuart S. P. Parkin"
        ],
        "submission_date": "2015",
        "SemanticScholarId": "b01baf5ae564efaa69fdd6d5fcb0b67624bcb919"
    },
    "1503.03765": {
        "title": "Electrical switching of an antiferromagnet",
        "authors": [
            "P. Wadley",
            "B. Howells",
            "J. Železný",
            "J. Železný",
            "C. Andrews",
            "V. Hills",
            "R. Campion",
            "V. Novák",
            "K. Olejník",
            "F. Maccherozzi",
            "S. Dhesi",
            "S. Martin",
            "T. Wagner",
            "T. Wagner",
            "J. Wunderlich",
            "J. Wunderlich",
            "F. Freimuth",
            "Y. Mokrousov",
            "J. Kuneš",
            "J. Chauhan",
            "M. Grzybowski",
            "M. Grzybowski",
            "A. Rushforth",
            "K. Edmonds",
            "B. Gallagher",
            "T. Jungwirth",
            "T. Jungwirth"
        ],
        "submission_date": "2015",
        "SemanticScholarId": "bd39110b7cf17e0dc1384c28822eeedd9ff434b7"
    },
    "1502.08028": {
        "title": "Blowing magnetic skyrmion bubbles",
        "authors": [
            "Wanjun Jiang",
            "P. Upadhyaya",
            "Wei Zhang",
            "Guoqiang Yu",
            "M. Jungfleisch",
            "F. Fradin",
            "J. Pearson",
            "Y. Tserkovnyak",
            "Kang L. Wang",
            "O. Heinonen",
            "S. T. te Velthuis",
            "A. Hoffmann"
        ],
        "submission_date": "2015",
        "SemanticScholarId": "d6e5d53a2f40bf44dff3ccb776c7b889e2a0e758"
    },
    "1309.4041": {
        "title": "Anomalous Hall effect arising from noncollinear antiferromagnetism.",
        "authors": [
            "Hua Chen",
            "Q. Niu",
            "A. Macdonald"
        ],
        "submission_date": "2013",
        "SemanticScholarId": "311d533cd45d3403fcf8abb7b56bb76826b3e211"
    },
    "1209.4480": {
        "title": "Robust formation of Skyrmions and topological Hall effect anomaly in epitaxial thin films of MnSi.",
        "authors": [
            "Yufan Li",
            "Yufan Li",
            "N. Kanazawa",
            "X. Z. Yu",
            "A. Tsukazaki",
            "Masashi Kawasaki",
            "Masakazu Ichikawa",
            "Xiaofeng Jin",
            "F. Kagawa",
            "Yoshinori Tokura"
        ],
        "submission_date": "2012",
        "SemanticScholarId": "87ef6c11df2860226aafd73ff2b885e2673fcc48"
    },
    "1203.2875": {
        "title": "Spin-Torque Switching with the Giant Spin Hall Effect of Tantalum",
        "authors": [
            "Luqiao Liu",
            "C. Pai",
            "Yulin Li",
            "H. Tseng",
            "D. Ralph",
            "R. Buhrman"
        ],
        "submission_date": "2012",
        "SemanticScholarId": "9782a75d3377cdcdc7f223bbac8a5be4128bcbe7"
    },
    "0902.1933": {
        "title": "Topological Hall effect in the A phase of MnSi.",
        "authors": [
            "A. Neubauer",
            "C. Pfleiderer",
            "B. Binz",
            "A. Rosch",
            "R. Ritz",
            "P. G. Niklowitz",
            "P. Böni"
        ],
        "submission_date": "2009",
        "SemanticScholarId": "3b101de56a306d2c025eea9479453bc79c7b5a74"
    },
    "cond-mat/9906160": {
        "title": "Spin Hall Effect",
        "authors": [
            "J. Hirsch"
        ],
        "submission_date": "1999",
        "SemanticScholarId": "229f27934ddeef56f520fc3c7b6ad51d4ece142c"
    }
}