{
    "2202.02687": {
        "title": "Cross-Channel Attention-Based Target Speaker Voice Activity Detection: Experimental Results for the M2met Challenge",
        "authors": [
            "Weiqing Wang",
            "Xiaoyi Qin",
            "Ming Li"
        ],
        "submission_date": "2022",
        "SemanticScholarId": "47d9f0e0d66dda55eaa7620f32e1b1a10a56353b"
    },
    "2110.13900": {
        "title": "WavLM: Large-Scale Self-Supervised Pre-Training for Full Stack Speech Processing",
        "authors": [
            "Sanyuan Chen",
            "Chengyi Wang",
            "Zhengyang Chen",
            "Yu Wu",
            "Shujie Liu",
            "Zhuo Chen",
            "Jinyu Li",
            "Naoyuki Kanda",
            "Takuya Yoshioka",
            "Xiong Xiao",
            "Jian Wu",
            "Long Zhou",
            "Shuo Ren",
            "Y. Qian",
            "Yao Qian",
            "Micheal Zeng",
            "Furu Wei"
        ],
        "submission_date": "2021",
        "SemanticScholarId": "416dab850fda842b13a4f28164514d98f836fff7"
    },
    "2106.08207": {
        "title": "Graph-based Label Propagation for Semi-Supervised Speaker Identification",
        "authors": [
            "Long Chen",
            "Venkatesh Ravichandran",
            "A. Stolcke"
        ],
        "submission_date": "2021",
        "SemanticScholarId": "e197dce74eb850428b98c1b5c5820464a7f8fd1f"
    },
    "2106.04624": {
        "title": "SpeechBrain: A General-Purpose Speech Toolkit",
        "authors": [
            "M. Ravanelli",
            "Titouan Parcollet",
            "Peter William VanHarn Plantinga",
            "Aku Rouhe",
            "Samuele Cornell",
            "Loren Lugosch",
            "Cem Subakan",
            "Nauman Dawalatabad",
            "A. Heba",
            "Jianyuan Zhong",
            "Ju-Chieh Chou",
            "Sung-Lin Yeh",
            "Szu-Wei Fu",
            "Chien-Feng Liao",
            "Elena Rastorgueva",
            "Franccois Grondin",
            "William Aris",
            "Hwidong Na",
            "Yan Gao",
            "R. Mori",
            "Yoshua Bengio"
        ],
        "submission_date": "2021",
        "SemanticScholarId": "b79cd3e0e2b154922b5cd16e1fbed9cb44e5a59f"
    },
    "2105.04065": {
        "title": "Voice Activity Detection in the Wild: A Data-Driven Approach Using Teacher-Student Training",
        "authors": [
            "Heinrich Dinkel",
            "Shuai Wang",
            "Xuenan Xu",
            "Mengyue Wu",
            "K. Yu"
        ],
        "submission_date": "2021",
        "SemanticScholarId": "4196bf6759de46afead544f63dbfbb32ce1e9b9c"
    },
    "2102.07445": {
        "title": "On training targets for noise-robust voice activity detection",
        "authors": [
            "Sebastian Braun",
            "I. Tashev"
        ],
        "submission_date": "2021",
        "SemanticScholarId": "2f825bd6fbb734ee19f038f7390c0ea9154bff46"
    },
    "2010.13886": {
        "title": "MarbleNet: Deep 1D Time-Channel Separable Convolutional Neural Network for Voice Activity Detection",
        "authors": [
            "Fei Jia",
            "Somshubra Majumdar",
            "Boris Ginsburg"
        ],
        "submission_date": "2020",
        "SemanticScholarId": "9c2e71301363b2b32569a9cb0af30bfc28c0c775"
    },
    "1906.03588": {
        "title": "rVAD: An Unsupervised Segment-Based Robust Voice Activity Detection Method",
        "authors": [
            "Zheng-Hua Tan",
            "A. Sarkar",
            "N. Dehak"
        ],
        "submission_date": "2019",
        "SemanticScholarId": "72eb5f52049ac2277a6d2502e8d88a34a5fcb4b8"
    },
    "1711.05355": {
        "title": "Automatic Conflict Detection in Police Body-Worn Audio",
        "authors": [
            "Alistair Letcher",
            "Jelena Trisovic",
            "Collin Cademartori",
            "Xi Chen",
            "Jason Xu"
        ],
        "submission_date": "2017",
        "SemanticScholarId": "083bcc9b17decd41517ab47fd64634de079c1af5"
    },
    "1409.1556": {
        "title": "Very Deep Convolutional Networks for Large-Scale Image Recognition",
        "authors": [
            "K. Simonyan",
            "Andrew Zisserman"
        ],
        "submission_date": "2014",
        "SemanticScholarId": "eb42cf88027de515750f230b23b1a057dc782108"
    }
}