{
    "partition": "test",
    "groundtruth": {
        "du2022noise": "2201.10693",
        "sisman2020overview": "2008.03648",
        "syang": "2004.13595",
        "yao2021wenet": "2102.01547",
        "dccrn": "2008.00264",
        "lmxue": "2207.00756",
        "hifigan": "2010.05646",
        "acvc": "2111.06601",
        "n2n1": "2109.10608",
        "sedis": "2001.10601",
        "asymloss": "2009.04323",
        "jcong": "2008.04265",
        "VQMIVC": "2106.10132"
    },
    "prediction": {
        "du2022noise": [
            "2201.10693",
            "2008.04265",
            "2112.04424",
            "2106.00992",
            "2008.03648"
        ],
        "sisman2020overview": [
            "2008.03648",
            "2201.10693",
            "2111.07116",
            "2109.10608",
            "2207.00756"
        ],
        "syang": [
            "2004.13595",
            "2008.04265",
            "2207.00756",
            "2201.10693",
            "2102.01547"
        ],
        "yao2021wenet": [
            "2102.01547",
            "2009.04323",
            "2004.13595",
            "2008.00264",
            "2111.07116"
        ],
        "dccrn": [
            "2008.00264",
            "2001.10601",
            "2102.01547",
            "2110.09625",
            "2111.07116"
        ],
        "lmxue": [
            "2207.00756",
            "2004.13595",
            "2111.07116",
            "2201.10693",
            "2008.04265"
        ],
        "hifigan": [
            "2010.05646",
            "2004.13595",
            "2008.04265",
            "2106.00992",
            "2001.10601"
        ],
        "acvc": [
            "2111.06601",
            "2111.07116",
            "2106.00992",
            "2106.10132",
            "2011.00316"
        ],
        "n2n1": [
            "2109.10608",
            "2111.07116",
            "2201.10693",
            "2207.00756",
            "2106.00992"
        ],
        "sedis": [
            "2001.10601",
            "2009.06122",
            "2008.00264",
            "2110.09625",
            "2009.04323"
        ],
        "asymloss": [
            "2009.04323",
            "2102.01547",
            "2111.07116",
            "2106.10132",
            "2008.03648"
        ],
        "jcong": [
            "2008.04265",
            "2201.10693",
            "2004.13595",
            "2111.07116",
            "2106.00992"
        ],
        "VQMIVC": [
            "2106.10132",
            "2207.00756",
            "2111.07116",
            "2011.00316",
            "2004.13595"
        ]
    }
}