{
    "elements": {
        "2211.03025_520a01a4c82a2a4ffe9a199156f237e6": "Document Root 2211.03025",
        "2211.03025_e353dbe42c8654f33588d4da0b517469": "Abstract",
        "2211.03025_0b2267c15c76fe3f56448144f4e89922": "Spoken language understanding (SLU) is a task aiming to extract high-level semantics from spoken utterances",
        "2211.03025_bb3fe0ef1ead58fb433a57b4d7467fb7": "Previous works have investigated the use of speech self-supervised models and textual pre-trained models, which have shown reasonable improvements to various SLU tasks",
        "2211.03025_66b4bf4f1f2ef3797f2e51f5cd18d363": "However, because of the mismatched modalities between speech signals and text tokens, previous methods usually need complex designs of the frameworks",
        "2211.03025_fd83a41f0483513ea59fddf3762f29e7": "This work proposes a simple yet efficient unsupervised paradigm that connects speech and textual pre-trained models, resulting in an unsupervised speech-to-semantic pre-trained model for various tasks in SLU",
        "2211.03025_ae78df3eb42e51b7048ee4e0cf4287bc": "To be specific, we propose to use unsupervised automatic speech recognition (ASR) as a connector that bridges different modalities used in speech and textual pre-trained models",
        "2211.03025_51f83ff8da94894d5a52e5a15154180b": "Our experiments show that unsupervised ASR itself can improve the representations from speech self-supervised models",
        "2211.03025_083724c3d1345c0586856578db3abc65": "More importantly, it is shown as an efficient connector between speech and textual pre-trained models, improving the performances of five different SLU tasks",
        "2211.03025_7758b999ea3565189455f529d5e45afe": "Notably, on spoken question answering, we reach the state-of-the-art result over the challenging NMSQA benchmark.",
        "2211.03025_cdfa14b00deb1e3fbf8f42e1cfb6d8ef": "unsupervised ASR, self-supervised learning, spoken language understanding",
        "2211.03025_0b79795d3efc95b9976c7c5b933afce2": "Introduction",
        "2211.03025_4d74542611769bd6f0bc9619fa7ce75a": "Transfer learning has been known as one of the major methodologies in the deep learning era",
        "2211.03025_7db06adccab50d2d9fef2888c081f4cd": "It has demonstrated its success in speech and natural language",
        "2211.03025_508c81c056c3be8c714aaf691da6d4e3": "\\cite{bert, baevski2020wav2vec}",
        "2211.03025_67ba9e1b3b67ff094c5442ebdcad7fc2": "In transfer learning, self-supervised learning (SSL) has been a large branch of studies that focuses on leveraging large amounts of unlabelled data",
        "2211.03025_b126aa7a50ebe19e66d33e94ab2d5334": "According to previous literature, SSL can learn to extract contextual representations that greatly improve the performances of various downstream tasks",
        "2211.03025_4e4c71de09a8624c5df9a2dda7446ca1": "\\cite{yang2021superb}",
        "2211.03025_36bc53ee58859ab40e4ba1fc9c47fa8a": "Many real-world tasks involve transforming one modality to another (e.g., image caption, speech recognition/understanding, songwriting, etc.)",
        "2211.03025_fb38b379c99db5b214b18fc15b20fc65": "\\cite{xu2015show, yu2016automatic, qian2022training}",
        "2211.03025_4bd7889d3fb9921878755ea7f8714e0d": "Usually, there is a need to understand both modalities in those tasks",
        "2211.03025_209684d705f4718324022e35d1b7b995": "Given the advances in pre-trained models, several previous works have shown significant improvements by simply applying the pre-trained models",
        "2211.03025_1969acd3dc4d0c224f2e6fcf6cfe6805": "\\cite{gomez2017self, baevski2019effectiveness, chang2021exploration}",
        "2211.03025_bea882746951b8b823700f58468dd879": "In their applications, pre-trained models over source modalities are easier to adopt.",
        "2211.03025_eeea279c53f15f885b45cd548c31e75e": "Spoken language understanding (SLU) is an example of modalities' transfer, which aims to infer the semantic meaning from spoken utterances.",
        "2211.03025_f1b253b315fd75072f3220c2b89308eb": "Conventional SLU methods usually adopt a pipeline that consists of an automatic speech recognition (ASR) module and a natural language understanding (NLU) module",
        "2211.03025_ef3a52dc222abe39455c4540cbd0453e": "\\cite{bastianelli2020slurp}",
        "2211.03025_3278ae53b63f2538160c88f3356b2c01": "However, in recent days, more researchers have started to focus on end-to-end modeling as it could avoid potential error propagation between the two modules",
        "2211.03025_a32b3b51ba2ecf1ada69790143464301": "Because end-to-end SLU involves both NLP and speech processing knowledge, previous studies also revealed that SSL in each modality could improve end-to-end SLU performances",
        "2211.03025_50315cbce8137261e37f44ac3a27cc3c": "Some works have investigated the joint pre-training with both speech and text modalities",
        "2211.03025_91d460c24a1561aaa43d9ce131e94214": "\\cite{bapna2021slam, bapna2022mslam}",
        "2211.03025_59fb84f021b0645c204a8113ae1a1c2c": "While for most other works, researchers adopted speech SSL as a feature extractor, shown to receive improvements in both performance and efficiency",
        "2211.03025_abf4e379e939031a3f3c716d3cd62c03": "\\cite{yang2021superb, dinarelli2022toward, borgholt2021we, chang2022exploration, translation, arora2022espnet}",
        "2211.03025_2d4cb2da16553cc035889a5859913d6e": "On the other hand, textual SSLs are difficult to integrate into end-to-end SLU because of the mismatched modalities",
        "2211.03025_06d9ef9e46ebb6ec14a4bfdfbc96147e": "Therefore, existing works usually need specific designs to utilize those textual pre-trained models, such as deliberation modules",
        "2211.03025_a060b1836299e2675f6ec8a6b1a58826": "\\cite{arora2022two, chung2021splat, huang2020leveraging}",
        "2211.03025_5af78326f60014ae942f3f31c428765d": ", two-stage decoding",
        "2211.03025_c8d830c51b9eacd001e0681d40011133": "\\cite{lai2021semi}",
        "2211.03025_fd6383547091313ad3d58d14a81c16b0": ", K-means clustering for",
        "2211.03025_cb0ebf90a8d915c06f9e5aa93eb1914b": "tokenization\"",
        "2211.03025_0f88f0a2c86db0f8f5f9cc2539b21a12": "\\cite{lin2022dual}",
        "2211.03025_8c646394c4addfac3b7698622c8ddcc7": "All approaches could get decent performances on some SLU downstream tasks",
        "2211.03025_b72350a1d64957d88ff5e944bc53e90d": "However, most of them complicate the training/inference procedure and need further fine-tuning with supervision when applied to downstream tasks",
        "2211.03025_eea7da2d8bfa7985b255b0d9855aab42": "To achieve a simple way of connecting SSLs between two modalities for SLU, this paper proposes a novel usage of unsupervised ASR (UASR) to bridge SSLs between two modalities in a fully",
        "2211.03025_ddaa20befe1a3c147ff2ee52314a87fb": "manner",
        "2211.03025_ce2533ade5cc97dcc765a113ae938bab": "We start with a base framework that applies UASR to augment the speech SSL model by considering unpaired textual information",
        "2211.03025_465eab9b55099c06e55098ef683be074": "Following that, we introduce the method that uses UASR to bridge speech and textual pre-trained models.",
        "2211.03025_332e874cb2c5d1813da68301f442ce79": "In this work, we focus on connecting wav2vec2",
        "2211.03025_a141bc16469b30f2722916d1becccff2": "\\cite{baevski2020wav2vec}",
        "2211.03025_78195af496c101e8ae672e98f1e3399f": "and a phoneme variant of ByT5",
        "2211.03025_cceefdba8abd770753c308b997d45982": "\\cite{phonemet5}",
        "2211.03025_b638b5aa5f4c5950fba110ec00417ac4": "with wav2vec-U 2.0",
        "2211.03025_4e7f790cb183486c92aaceaa108aa9f3": "\\cite{liu2022towards}",
        "2211.03025_5300f8543d205fa32af100bdc290a0b4": "Our experiments validate the advantages of our proposed methods in various tasks and settings",
        "2211.03025_8c012419dbbed17f23d760adf36ce7f5": "Notably, we also reach the state-of-the-art performance on the challenging NMSQA benchmark on spoken question answering",
        "2211.03025_5058f1af8388633f609cadb75a75dc9d": ".",
        "2211.03025_1b8beac96733a54f513a835e96a9b592": "\\begin{figure*}[t]\n  \\centering\n  \\vspace{-20pt}\n  \\includegraphics[width=0.95\\linewidth]{uasr_application.pdf}\n  \\vspace{-10pt}\n  \\caption{The comparison between different frameworks: (a) the application of speech SSL models as a feature extractor to downstream tasks, discussed in Sec~\\ref{sec: background}. (b) the framework of using UASR as an augmentation module to the speech SSL, introduced in Sec~\\ref{ssec: uasr-ssl}. (c) the framework of using UASR as a connector to utilize a pre-trained text model for downstream tasks, proposed in Sec~\\ref{ssec: uasr-connector}.}\n  \\vspace{-15pt}\n  \\label{fig:framework}\n\\end{figure*}",
        "2211.03025_2ba0c1d2f0f117d4512ef6170fe0e015": "Methodology",
        "2211.03025_a9ded1e5ce5d75814730bb4caaf49419": "Background",
        "2211.03025_3cbad4d8989ae42c78fb1c2d525776b9": ": The SSL task is to find better speech representation for downstream tasks",
        "2211.03025_d32d37913d080c820cc49bc5f36ab5b5": "Previous SSL-related works usually utilize a speech-only corpus",
        "2211.03025_e559a39d7e0ba7d9b7991ab897d32ea8": "$\\mathcal{D}_{\\text{speech}}$",
        "2211.03025_6496af9c5798195c1b3e753f909239dd": "The encoder of the SSL model (i.e.,",
        "2211.03025_8824595f458085fe3bf467c4228300fc": "$f(\\cdot)$",
        "2211.03025_595ee636d53856b548c13644b99c740c": ") is primarily used, after training with designed self-supervised objectives",
        "2211.03025_71e97de845ac1655be37cec2c5b12014": "Given a speech signal",
        "2211.03025_7827a02c3d1561a1d013597e35566cbb": "$\\mathbf{X} \\in \\mathcal{D}_{\\text{speech}}$",
        "2211.03025_5da7171ed0788cbeeae52a7d894a56bb": ", the encoder",
        "2211.03025_5a6c093b5f54ca0974067982efc8f2b7": "generates a hidden representation",
        "2211.03025_333bd489f2aefb7c519a7e3da2fa8378": "$\\mathbf{H} = (h_1, h_2, ..., h_T)$",
        "2211.03025_a29f17caa3e965b909d1aef183a202e4": ", where",
        "2211.03025_2f118ee06d05f3c2d98361d9c30e38ce": "$T$",
        "2211.03025_6b4effe9641010fbf752796449447d11": "is the number of frames of the representation",
        "2211.03025_51d57b0acdbd04299fbe5ad89221b87b": "As illustrated in Fig.",
        "2211.03025_47408740fea5a10fbbd74cd74a5d5382": "(a), representation",
        "2211.03025_930b956ef51654e0669455a2cdd62fb5": "$\\mathbf{H}$",
        "2211.03025_ebadbe0b39b727044142cc825fb02ba7": "is used as features for an additional model, when applying to downstream tasks.",
        "2211.03025_12b4d20e893dfc5ab03c489b17b0de00": ": Unsupervised ASR focuses on utilizing unparallel speech and text to realize speech recognition systems",
        "2211.03025_52294f9045816d20191d31186a73dc56": "Before the application of SSLs, previous methods have investigated the direction by learning acoustic-text alignment, adversarial networks, and quantized auto-encoding",
        "2211.03025_42c7c17c6797093b30665e8aa7dde146": "\\cite{chen2019completely, yeh2018unsupervised, liu2020towards}",
        "2211.03025_d6bc7c374633434768149e90c7d435ef": ": Extended from its previous version",
        "2211.03025_22c23dd5bea6a6e01b55a51f9a145b1c": "\\cite{baevski2021unsupervised}",
        "2211.03025_de87b8952c041ad1d74793e86ff6aae8": ", Wav2vec-U 2.0 is the state-of-the-art model in UASR, which is trained in an end-to-end manner",
        "2211.03025_0c6b436dbc1ba0b8d6a0149471f872b8": "In the method, SSL (i.e., wav2vec2) is employed as a feature extractor to extract hidden representation",
        "2211.03025_dd5bff875ed9ad942ac26dc14decbf8a": "The later setup follows generative adversarial training",
        "2211.03025_a6ba0a5ed91ad0a84b695e8ce84cd356": "The generator",
        "2211.03025_68a463cbf8842017bbbab8ca879333c7": "$\\mathcal{G}$",
        "2211.03025_4c144b6052db6f9b68c8594899c601a2": "takes the segmented acoustic features to generate pseudo phonetic sequences, while the discriminator",
        "2211.03025_db5f7b3e9934fbc5a2859d88c4ba84a3": "$\\mathcal{C}$",
        "2211.03025_c2566205d713dc99a54018a7870a4b37": "focuses on distinguishing the pseudo phonetic sequence from generator",
        "2211.03025_e595da9631a2dfb03d0048c6c3bec7ab": "$\\mathcal{G}(\\mathbf{H})$",
        "2211.03025_20db16323e0853a8774699e4b2a63fd2": "and the real phonetic sequence",
        "2211.03025_23f3aecb7fcd139009be9a162be26b77": "$\\mathbf{Y}^u \\in \\mathcal{D}_{\\text{text}}$",
        "2211.03025_7805c32557871f0c160d2d70a4650761": "Noted that",
        "2211.03025_7c546f380643ec6c63837bd809e73c0e": "$\\mathcal{D}_{\\text{text}}$",
        "2211.03025_328c743e0271d85bc3f78557dc18aafd": "is a text-only corpus, which is unpaired with",
        "2211.03025_17f6b595a3b9a0e7c108c5d0c44b6144": "Apart from the adversarial loss, wav2vec-U 2.0 also utilizes several other types of losses (i.e., gradient penalty",
        "2211.03025_054939ab2c639ccb9e596e8a42ca480b": "$\\mathcal{L}_{\\text{gp}}$",
        "2211.03025_862c67d66ec91c59224efac09221e784": ", segment smoothness",
        "2211.03025_1df51cbd38487f40dae2ffa9c583e9d3": "$\\mathcal{L}_{\\text{sp}}$",
        "2211.03025_cf84d3bab68d5595c0e61ff25cf682de": ", phoneme diversity",
        "2211.03025_9857d9db30074055658db2b7e7c7a8a1": "$\\mathcal{L}_{\\text{pd}}$",
        "2211.03025_3de71b63340ab8d2524a258abeaba924": ", and auxiliary K-means clusters",
        "2211.03025_ac338cdb8cda0290f8497dfdbcecbda8": "$\\mathcal{L}_{\\text{ss}}$",
        "2211.03025_9b2d5a803a24aeebc1d84d7a43d66732": "from Mel frequency cepstral coefficients (MFCC)) to stabilize the training",
        "2211.03025_ad4c54b864c01957a9f251677c04183e": "The final optimization target is formulated as:",
        "2211.03025_f19066c1896240f230af541735499450": "\\begin{equation}\n\\begin{split}\n    \\label{eq: wav2vec-u2}\n    \\min_{\\mathcal{G}} \\max_{\\mathcal{C}} & \\mathbb{E}_{\\mathbf{Y}^u} [\\log \\mathcal{C}(\\mathbf{Y}^u)] - \\mathbb{E}_{\\mathbf{H}} [\\log(1 - \\mathcal{C(\\mathcal{G}(\\mathbf{H}))})] \\\\\n    & + \\lambda \\mathcal{L}_{\\text{gp}} + \\gamma \\mathcal{L}_{\\text{sp}} + \\eta \\mathcal{L}_{\\text{pd}} + \\delta \\mathcal{L}_{\\text{ss}},\n\\end{split}\n\\end{equation}",
        "2211.03025_567904efe9e64d9faf3e41ef402cb568": "where",
        "2211.03025_e5552f58c8ed59d7fb70aa9f7c9ec842": "$\\lambda, \\gamma, \\eta, \\delta$",
        "2211.03025_292e89dd64d9ca96c35430a04d73c406": "are the weights for losses.",
        "2211.03025_89d9ce70a014252e580e2b44a6b68548": "UASR with SSL provides the foundation of our following investigation",
        "2211.03025_21681ccce8d2b68b4707b51b6e9f8ad1": "In later sections, we primarily focus on a simplified version of wav2vec-U 2.0 that is without auxiliary cluster prediction (i.e., remove",
        "2211.03025_231cb07c56ef0f14d722140514bff617": "), as we empirically find the training is harder to converge with the proposed version in",
        "2211.03025_d3ed97478e5bb62df6a73642fb3eb2cf": "Problem Formulation",
        "2211.03025_feaab97b2c4fb80ab18e358659c74198": "As speech SSLs train on a large number of speech signals from",
        "2211.03025_6b579e69678c3cb5c3accfc3c6d3b53e": ", it has shown impressive performances in several speech tasks",
        "2211.03025_f8eaedfcc2a3e0a6bae899550f75be21": "\\cite{yang2021superb, tsai2022superb}",
        "2211.03025_0c3996c24241afa482f64e8f9b703e3f": "However, recent works also reveal that speech SSLs cannot handle some high-level semantic tasks (e.g., spoken question answering)",
        "2211.03025_426a5ff7c7b14928d60c8adcc9acd973": "To reach reasonable performances, the framework needs the following textual pre-trained model",
        "2211.03025_f6413e2673ee0ba35a3e434b2ad51ee5": "$f_{\\text{text}}$",
        "2211.03025_023136296873cecf0eddd3aa7dc567c8": "that trains on text-only corpus",
        "2211.03025_93890d00a22bc16357299f69868b0201": "To match the embeddings in textual pre-trained models, previous work applied K-means clustering to convert the speech SSL features into cluster IDs, which are further used as a token ID for the textual model",
        "2211.03025_95939da53aaf9cab5af3a5d7c6fb4fc5": "The sequential application of speech and textual pre-trained models results in an issue of modalities mismatch between speech and text token IDs, so a fine-tuning stage is necessary to connect these modalities",
        "2211.03025_7aefcecda73e6969b672941164d51045": "On the other hand, our method can connect both SSL models in the pre-training stage without fine-tuning thanks to UASR, and build an",
        "2211.03025_f828277b9b63a7409a02b5bd2168ae5b": "straightforwardly.",
        "2211.03025_7c033aa21e8a2232531a74f4889b430b": "In the following subsections, we first add UASR as an augmentation module to the speech SSL model as a base framework, resulting in a speech-to-text pre-trained model",
        "2211.03025_be2081ca85be8b98895b43eb5838f000": "Then, we further extend it by combining a textual pre-trained model, where we utilize UASR as a connector and contract a speech-to-semantic pre-trained model.",
        "2211.03025_9399c1fce9154541c6ee71269a9a84e2": "UASR as an Augmentation Module",
        "2211.03025_37b0abd9c22d3502f98869b0f707743d": "In this subsection, we propose using UASR as an augmentation module for the speech SSL model for the following reasons.",
        "2211.03025_0f08f6b38cf5e59043e7db5500377b64": ": As discussed in Sec",
        "2211.03025_48f6e9e2f826b98566db5598211af8c3": ", the UASR are jointly trained with inputs that include both",
        "2211.03025_be5d5d37542d75f93a87094459f76678": "and",
        "2211.03025_196c6e818eee01dbe7b3781f06193b95": "As discussed in Sec.",
        "2211.03025_155f724954564cb756f588edf75d3a52": ", adding an unsupervised ASR network maintains the unsupervised property of the whole model, which keeps the benefits of learning from a vast amount of unsupervised data.",
        "2211.03025_b62096207b380e041aa4b47046c7ed0d": ": The incorporation of text-only corpus",
        "2211.03025_99d4492cfc8bdc7e35891aaf418b1a7f": "is the major difference between speech SSL and the proposed method",
        "2211.03025_cfdc86c5ef23e313d05311fa27953cb1": "According to (",
        "2211.03025_76501284e0ea655d387f82a6a754b033": "), the textual information",
        "2211.03025_5474d5ad49d775d5be6b38407d20875f": "$Y^u$",
        "2211.03025_eb8640cc4cd425198a4f92ac132a5bcc": "is explicitly applied with the adversarial objective.",
        "2211.03025_0f51e5a000bfc7b6ec6e45fa2083027b": ": To keep the performance stable for various tasks, we can always apply the original speech SSL with the UASR representation.",
        "2211.03025_0ccfe5be0b16474da2ea438d0c6a919c": "The application of UASR follows the illustration of Fig.",
        "2211.03025_df5e76fc6e0cf33469544ef57ad8cd17": "(b)",
        "2211.03025_165e486f50318efb515f944aa5dfeac8": "In short, the augmented model is defined as follows,",
        "2211.03025_c8c3f73414972cc72adc3b88c7e0422c": "\\begin{equation}\n    \\label{eq: uasr_ssl}\n    f_{\\text{UASR}}(\\mathbf{H}) \\triangleq (\\mathbf{H}, \\text{UP}(\\mathcal{G}(\\mathbf{H}))),\n\\end{equation}",
        "2211.03025_6b6683ba13edc01e91ac4fa76ac8c53a": "$\\text{UP}(\\cdot)$",
        "2211.03025_9774c2b89829a0e743a20daf2fa62b26": "is an upsampling function to match the resolution of",
        "2211.03025_a4704fd35f0308287f2937ba3eccf5fe": "The",
        "2211.03025_3bcc2fd71ef0935e43b2ef346fe8f824": "$f_{\\text{UASR}}(\\mathbf{H})$",
        "2211.03025_4f2d1fae77331b81f0a21f8185ec19f1": "is used as the input of downstream models for various tasks.",
        "2211.03025_1bfe57d150d58583d44df39b0d3484fd": "UASR as a Connector",
        "2211.03025_4cd28de907145bc8e6813ae81fa0c3da": "and Sec.",
        "2211.03025_c05090f0a8707f8582b0e854f072af5b": ", the modalities mismatch issue blocks constructing pre-trained speech-to-semantic models in an unsupervised manner",
        "2211.03025_ebd5adeb2dc306dab15632b544cdf20b": "Since UASR targets conducting recognition in an unsupervised fashion, it could naturally be a glue to connect the acoustic and textual pre-trained models",
        "2211.03025_d5bd9e710f8deeb124e502cc3de8166d": "We argue that using UASR as a connector would have three more benefits, apart from the mitigation of the modalities mismatch issue.",
        "2211.03025_ca0a0c8e7708773e0e70a708c55adb57": ": Similar to",
        "2211.03025_4ae3450930a4c2e3dbfe890ce236428a": "$f_{\\text{UASR}}$",
        "2211.03025_7109f6dd942cf26d288485503650cff2": "in Sec.",
        "2211.03025_a8c34cffa0ed573d43de5c6d85834dd0": ", adding UASR as a connector can still maintain the unsupervised property of the whole model.",
        "2211.03025_d90030ee6001ab2df3cc487a6fffd614": ": As explained in Sec.",
        "2211.03025_c7fb5eb468af5eed821d084d9c9b08cf": ", the UASR module can introduce implicit textual knowledge from the adversarial objective",
        "2211.03025_188352b463d4f7a5afa3ce7b2a444be2": "On the other hand, when applying UASR as a connector, it can adopt explicit textual resources that hold semantic information from the pre-trained text model",
        "2211.03025_76c9602559465fb10e8ffbb598bd9369": ": As previous methods usually need fine-tuning to mitigate the modalities mismatch between speech and text modalities, using UASR as a connector can relax the requirement for fine-tuning since the output of UASR is a text (phoneme)-level distribution.",
        "2211.03025_75b070d32e416f57cb438eda74054dfc": "The application of the UASR connector follows Fig.",
        "2211.03025_2756d240dd4ae4350bb92e09ce95797f": "(c)",
        "2211.03025_d67356b045763f57785a89f84ce546a0": "The augmented model is defined in a similar manner to",
        "2211.03025_17349b18ec9ea5c2d535a362a2d820b7": ", as follows,",
        "2211.03025_a3b0261e195fb9d8220cacd961e504d5": "\\begin{equation}\n    \\label{eq: uasr_connector}\n    f_{\\text{speech\\_text}}(\\mathbf{H}) \\triangleq (\\mathbf{H}, \\text{UP}'(\\mathcal{G}(\\mathbf{H})), \\text{UP}'(f_{\\text{text}}(\\mathcal{A}[\\mathcal{G}(\\mathbf{H})]))),\n\\end{equation}",
        "2211.03025_eb13a88d27918037558fd3450df3e83a": "$\\text{UP}'(\\cdot)$",
        "2211.03025_2bb612101cc607107d95e3e908c646fc": "is another upsampling function to match the resolution of",
        "2211.03025_7651ba0e8e29ee7537841a819041a172": "$\\mathcal{A}$",
        "2211.03025_672db0d1623dbd241d611c9a035e1d30": "is an assignment procedure that assigns phone tokens to each frame, given a phonetic posteriorgram.",
        "2211.03025_ea771a7a932d5ac625002df279bc0697": "can be a",
        "2211.03025_cc6a176bc80fdf292f529b18ebcbe37d": "$\\mathrm{GumbleSoftmax}$",
        "2211.03025_fda096f64bb07f248cc6d94ce9915a6f": "module to keep the differentiable property, but it can also be an argmax operation for simplicity",
        "2211.03025_438b3d81c28c5f9696d706c8fa09d123": "Similar to Sec.",
        "2211.03025_3834d9c55f761f7ceab4df37877d360a": ", the",
        "2211.03025_b9e719677b042dba85d7e2e45cd3388c": "$f_{\\text{speech\\_text}}(\\mathbf{H})$",
        "2211.03025_fd1fb494271c872ca6b688dd1a49ede0": "is used as the input of downstream models.",
        "2211.03025_4829262cecb9828817b33e0f9c907f91": "Experiments",
        "2211.03025_922201349a90c140e102732097e41d13": "Downstream Tasks and Datasets",
        "2211.03025_af84a1e77c29797293ede9bf9eeaf54f": "To fully investigate the proposed methods, we conduct experiments in two folds: the first freezes the parameters of the pre-trained model; the second fine-tunes the textual pre-trained model.",
        "2211.03025_6218d54009e3d39cc5f643e6c048710d": ": In the freeze setting, we follow the exact setting of SUPERB benchmark",
        "2211.03025_72f36ac0a79c56bde7f577638b15caba": "As discussed in the previous section, we primarily focus on understanding tasks, including intent classification (IC), emotion recognition (ER), and speech translation (ST)",
        "2211.03025_dedfaabb4af3ea29306614b1b603b6f9": "However, as UASR are designed for recognition tasks, we also conduct experiments in ASR and phone recognition (PR)",
        "2211.03025_8ec5e26b3a21b7b765ad095bdc1215c9": "Meanwhile, we carry out the speaker identification (SID) task to verify if the UASR and the pre-trained text model are effective for semantic-related tasks.",
        "2211.03025_c9fc211abade3c4a3b0a0ff5595570a8": ": In the fine-tuning setting, we only conduct experiments that fine-tunes the textual model to match the configuration in",
        "2211.03025_5b3085e6f5165f6e18fd0fe5d2dbf2a1": "and to avoid joint training of a large model",
        "2211.03025_8f65a23d21470deea698e691b5f02b1d": "We adopt ESPnet",
        "2211.03025_7ace5b856c26e5138bab1ffc93278cc8": "\\cite{inaguma2020espnet, arora2022espnet}",
        "2211.03025_8c897252df5626bda41a746b844e950f": "that can support stronger downstream models",
        "2211.03025_a0d6279bc973a925989993aad6923b7f": "We intentionally select some different datasets that are larger than the ones in the SUPERB benchmark, evaluating the proposed method apart from the potential over-fitting issue in low-resource scenarios",
        "2211.03025_39ec6aa0554a10e8cb05358ed6a5e2b6": "Similar to the freeze setting, we focus on understanding tasks, including IC, ER, ST, and slot-filling (SF)",
        "2211.03025_37a2bdb177d94c763867a4bdd9fff514": "We adopt SLURP",
        "2211.03025_a09931985321aff7da3db2091aaad555": "for IC and ST, IEMOCAP for ER",
        "2211.03025_6ced65face999e4e780c73e30eaaef9d": "\\cite{busso2008iemocap}",
        "2211.03025_682277f298a9895b785425539b58cf55": ", and CoVOST2 for ST",
        "2211.03025_4140f54cd025a787f4e44471e20ec7ac": "\\cite{wang2021covost}",
        "2211.03025_5750b6ade0af6eb323017c2279decf57": "In addition, We also tested on a publicly available spoken question answering (SQA) NMSQA dataset",
        "2211.03025_5140851000a25500a15df9c475e9db5f": "Three test sets included are derived from SQuAD",
        "2211.03025_7c806f16cf09e3ab91b1e54ce2be2a45": "\\cite{rajpurkar2016squad}",
        "2211.03025_0997f670eeaa7063402cf66d9bc0baf7": ", NEWSQA",
        "2211.03025_52875b20f38067e5a00658156a03bb1b": "\\cite{trischler2016newsqa}",
        "2211.03025_60fd1e3b3efe81626ded96c2b16a4eba": "and QuAC",
        "2211.03025_d9adcbe1db8236a99f20c7ea3116aef7": "\\cite{choi2018quac}",
        "2211.03025_01edf4d371afbc4c9844b3dd184997fa": ", whereas the latter two are reported together as out-of-domain (OOD) samples.",
        "2211.03025_5d4aa5e42b9d7396cc1e8d481a326892": "\\begin{table}\n\\centering\n\\caption{\\label{tab: freeze exp} Freeze setting experiments with UASR and PT5: pre-trained models are frozen during the training. The ``+UASR\" option utilizes the method explained in Sec.~\\ref{ssec: uasr-ssl}, while the ``+UASR +PT5\" option utilizes the method showed in Sec.~\\ref{ssec: uasr-connector}. }\n\\begin{tabular}{l|ccccc}\n\\toprule \nSSL & PR($\\downarrow$) & ASR($\\downarrow$) & IC($\\uparrow$) & ST($\\uparrow$) & SID($\\uparrow$) \\\\ \n\\midrule\nwav2vec2 & 5.51 & 3.79 & 94.38 & 13.01 & \\textbf{83.69}\\\\\n\\quad +UASR & \\textbf{4.53} & \\textbf{3.76} & 94.33 & 13.00 & 82.85 \\\\\n\\quad +UASR +PT5 & 4.68 & 3.97 & \\textbf{94.88} & \\textbf{13.53} & 82.74 \\\\\n\\bottomrule\n\\end{tabular}\n\\vspace{-15pt}\n\\end{table}",
        "2211.03025_2407051aab75cf3f178323fc0762dd05": "\\begin{table*}\n\\centering\n\\caption{\\label{tab: fine-tune exp} Fine-tuning setting experiments with UASR and PT5: textual pre-trained models are jointly fine-tuned with downstream models during training. \\textbf{B} utilizes the method explained in Sec.~\\ref{ssec: uasr-ssl}, while \\textbf{D} utilize the method showed in Sec.~\\ref{ssec: uasr-connector}. Others models (i.e., \\textbf{A} and \\textbf{C}) and more detailed configurations are introduced in Sec.~\\ref{ssec: experimental setings}.}\n\\begin{tabular}{l|cc|cccc}\n\\toprule \n & Connector & Text Model & IC($\\uparrow$) & SF($\\uparrow$) & ER($\\uparrow$) & ST($\\uparrow$) \\\\ \n\\midrule\n\\textbf{A} & /\\ & /\\ & 82.82 & 65.82 & 66.35 & 22.1 \\\\\n\\textbf{B} & UASR & /\\ & 82.93 & 64.93 & 64.11 & 22.2 \\\\\n\\textbf{C} & K-means & PT5 & 86.41 & 71.70 & 72.61 & 22.5 \\\\\n\\textbf{D} & UASR & PT5 & \\textbf{87.10} & \\textbf{74.03} & \\textbf{73.57} & \\textbf{24.3} \\\\\n\\bottomrule\n\\end{tabular}\n\\vspace{-15pt}\n\n\\end{table*}",
        "2211.03025_220ed546e827681fb04afb62724dc42d": "\\begin{table}\n\\centering\n\\caption{\\label{tab: ablation exp} Effect of different textual pre-trained models when using UASR as a connector: \\textbf{E} employs a T5 architecture with randomized parameters; \\textbf{F} uses the original ByteT5; \\textbf{D} applies the phoneme T5 introduced in Sec~\\ref{ssec: experimental setings}.}\n\\begin{tabular}{l|c|cccccc}\n\\toprule \n & Text Model & IC($\\uparrow$) & SF($\\uparrow$) & ER($\\uparrow$) & ST($\\uparrow$) \\\\ \n\\midrule\n\\textbf{E} & RT5 & 86.61 & 71.83 & 72.19 & 23.9  \\\\\n\\textbf{F} & TT5 & 85.93 & 72.31 & 72.19 & \\textbf{24.6}  \\\\\n\\midrule\n\\textbf{D} & PT5 & \\textbf{87.10} & \\textbf{74.03} & \\textbf{73.57} & 24.3  \\\\\n\\bottomrule\n\\end{tabular}\n% \\vspace{-15pt}\n\\end{table}",
        "2211.03025_1183f006cafff6b8a90c57df1d15c2ab": "\\begin{table}\n\\centering\n\\caption{\\label{tab: sqa exp}  Effect of different textual pre-trained models for SQA when using UASR as a connector. The Longformer model is the state-of-the-art model in \\cite{lin2022dual}.}\n\\begin{tabular}{l|c|cc|cc}\n\\toprule \n& \\multirow{2}{*}{Text Model}  & \\multicolumn{2}{c|}{SQuAD}& \\multicolumn{2}{|c}{OOD}  \\\\ \n\n& & AOS($\\uparrow$) & FF1($\\uparrow$) & AOS($\\uparrow$) & FF1($\\uparrow$) \\\\\n\\midrule\n\\cite{lin2022dual} & Longformer & 49.1 & 55.9 & / & /\n\\\\\n\\textbf{F} & TT5 & 56.0 & 61.5 & 38.4 & 42.4 \\\\\n\\midrule\n\\textbf{D} & PT5 & \\textbf{65.8} & \\textbf{69.7} & \\textbf{42.1} & \\textbf{46.2} \\\\\n\\bottomrule\n\\end{tabular}\n\\vspace{-15pt}\n\\end{table}",
        "2211.03025_aa66d95e83ccb800b2bfb705185b36ba": "Experimental Settings",
        "2211.03025_efca547ae6f37daf101e0132704e38bc": ": Given that the UASR model is based on wav2vec2",
        "2211.03025_ee0a82aa5c80341ec6d47db4ba8010e2": ", we adopt pre-trained wav2vec2 that trained on LibriLight",
        "2211.03025_333ec17e45dd98d91d1e7e4833523a57": "\\cite{kahn2020libri}",
        "2211.03025_3c8fa38dafcca67310cfbf9c8763b92e": ": To keep the same as",
        "2211.03025_cf67f3dd31df9b70e630ff9aa141c737": ", we utilize Librispeech speech data for the speech-only corpus",
        "2211.03025_4a5ec10fe5f483e25a00f8637d2f1b3c": "and Librispeech language modeling data for the text-only corpus",
        "2211.03025_c94c984707985cdcb0c68c3210f8eef4": "As noted in Sec",
        "2211.03025_7f6d59c971660980539b871320b8f6b4": ", we do not use",
        "2211.03025_ccd5ad35e5bc991b7929b8da39b2b436": "For other settings, we use the hyper-parameters released on Fairseq.",
        "2211.03025_853ae90f0351324bd73ea615e6487517": ":",
        "2211.03025_15aae9b196cda6e26bf6918fb7088b35": ", we select PhonemeT5 (PT5)",
        "2211.03025_f7faef88bbd01e98e96ccf843ac801fd": "as our main textual pre-trained model, because it has the same token space as our UASR model",
        "2211.03025_59e82251963ab1bedbcc5b96b11727f7": "PT5 is a variant of ByT5",
        "2211.03025_5044dcb2183f819c317da3144eb0c0b7": "\\cite{xue2022byt5}",
        "2211.03025_1be7ec2262294de083755bfcb4dbd4ec": ", which uses phonemicized text",
        "2211.03025_ede23817aed72e76514ac06d5821c518": "as input with the span reconstruction objective.",
        "2211.03025_07ee8ced392b391a8fb012e2fb3a81c0": ": For the freeze setting, aligned with Fig.",
        "2211.03025_4e27870fa687da766a9b9ee403acf5db": ", we compare the models in three settings, including speech pre-trained model (i.e., wav2vec2), speech pre-trained model with UASR, and speech pre-trained model with UASR + textual pre-trained model (i.e., PT5)",
        "2211.03025_3f75bc3249ac5ae2c65b6710c749d994": "For the fine-tuning setting, we compare four settings:",
        "2211.03025_462a115a40954ff90a63325a3793aba3": "utilizes only the speech pre-trained model;",
        "2211.03025_a42dd9bf321b2b5e1916fd0b3c11fdad": "applies UASR as an augmented module to the speech pre-trained model;",
        "2211.03025_a2f0f116006df7998af93f95d5c9e75f": "employs K-means as a connector between speech and textual pre-trained models",
        "2211.03025_9eecb7db59d16c80417c72d1e1f4fbf1": ";",
        "2211.03025_9922b6de8634429dab0c676cbe07b541": "uses UASR instead of K-means as a connector",
        "2211.03025_00d1fea29a3a04973e9d419d20b6e397": "To further investigate the effects of different pre-trained text models, we provide two other models with the same network architecture, namely randomized T5 (RT5) and textual T5 (TT5)",
        "2211.03025_adcc7208eaf57b3eb032cae66ef54ca9": "RT5 is a model with the same architecture as PT5 but with randomized parameters",
        "2211.03025_2a333e3963fa923448b3105bb9c33eb1": "TT5 is the original version of ByT5 that is pre-trained on text data",
        "2211.03025_c78a5e06c1dba9ccb975a6deca8ad694": "Because of the token mismatch (i.e., phone tokens from UASR and byte-level tokens from ByT5), we utilize a randomly initialized dictionary to map UASR's phone tokens into bytes, similar to the K-means approach",
        "2211.03025_65ac574a52781cbe53689e3f1fa434f9": "Given the same framework as",
        "2211.03025_3f8db846a2ca9a285287b9e8a1b27d63": ", we name",
        "2211.03025_bed41888aee98a7d4bbfc7c2a3f7635e": "as the one with RT5 and",
        "2211.03025_52c8c127546e12a412a4085a4157b6f6": "as the one with TT5",
        "2211.03025_9fdf8dfdfe6f825290c347f1427e4d3e": "Except for SQA which utilizes whole pre-trained models (i.e., both encoder and decoder), other tasks only employ the encoders of the T5 variants (i.e.,",
        "2211.03025_c0cb5f0fcf239ab3d9c1fcd31fff1efc": ",",
        "2211.03025_8a0e2b549d223aba55a866c38d1c9275": ", and",
        "2211.03025_ce96ce64475d88003b81a20710c10f5e": ").",
        "2211.03025_ceaa47905061f4fc935944adf7be5259": ": For the freeze setting, we follow exact settings as the SUPERB public benchmark, which adopts simple downstream models (e.g., stacked linear or recurrent layers)",
        "2211.03025_7c113a786c424a332894c4dcee8a3175": "For the fine-tuning setting, we utilize ESPnet",
        "2211.03025_a393ccd9d8ad15576fea621d54a94c68": "\\cite{arora2022espnet, inaguma2020espnet}",
        "2211.03025_4c25e524368cf170f8e186db49edd99f": "for the downstream models except for SQA",
        "2211.03025_3572cf68da300728b81668b0d535b6d9": "For IC, SF, and ER, we adopt a conformer-based encoder-decoder network with the hybrid connectionist temporal classification (CTC)/attention style of training",
        "2211.03025_7c69097a8648781a3392ee86581e7ec3": "\\cite{guo2021recent, watanabe2017hybrid}",
        "2211.03025_dd4e7080cb6874d6ecbc33d7fa70851d": "While for ST, we adopt a transformer-based encoder-decoder with auxiliary ASR loss computed from CTC",
        "2211.03025_a17607ec8e64ef3579f5f7c6acf7d024": "Detailed network settings follow the corresponding configuration.",
        "2211.03025_c6aa19525a1453fc7104cba718678010": "For classification tasks like IC and ER, we also include ASR transcriptions as a joint learning objective",
        "2211.03025_be16c83bf9c80b906bbc922f03123e35": "For all models in ESPnet, we apply specaugment to the hidden states from pre-trained models",
        "2211.03025_e31e7718eddd1ccd489dd915988a97b4": "For SQA, it is difficult to hold the whole speech SSL features for the spoken context of answers",
        "2211.03025_43f06d52bd845e4af5b92eb6b88162e2": "Therefore, we employ a two-step approach",
        "2211.03025_02c301391bfa1277d05349f7c25cc8cd": "Specifically, questions and contexts are converted into time-coded phoneme sequences by UASR",
        "2211.03025_25bf66b584fd13c853fea7b7e9357bc1": "Given questions and contexts, the PT5 is fine-tuned to predict answer time spans in the context",
        "2211.03025_b9d47e954de1d1c8838ff9c95f997e86": "The model is trained for 3 epochs with a 3e-4 learning rate and the best model is selected based on the performances on the development set.",
        "2211.03025_d9bdd8ec3b2a11e65e836c5435f2a3d9": ": For PR, we adopt phone error rate (PER), while for ASR, we utilize word error rate (WER)",
        "2211.03025_5dc25ff40fe4d108efc31c1c4f638f72": "For IC and ER, we employ the accuracy rate",
        "2211.03025_c9740d3ffeef0b9935284711abf97091": "For slot-filling, we apply the slot-type F1 score",
        "2211.03025_dbfb2fca53573cf7efa0d48a66bc39ca": "For ST, we use the BLEU score",
        "2211.03025_f41dac38d74d0d82bbade650db64641e": "For SQA, we adopt the same evaluation metrics as",
        "2211.03025_9ad5f90b39cc648932e7a53df0d84260": ", including the area overlapping score (AOS) and frame F1 (FF1)",
        "2211.03025_ab761150d4033138082fedd51d37dc3b": "Note that when the answers cannot be extracted from the given context, we set AOS and FF1 to 0.",
        "2211.03025_d1fb541327a140ceab489f7029524517": "Results and Discussion",
        "2211.03025_a8e9871ae39421409854fcb5f8826690": "We first discuss the results of the freeze setting as shown in Table",
        "2211.03025_ae0c54ab92e16dfffe5f04e7b480e7f6": "As UASR is optimized for PR, it is reasonable to have better performances in PR",
        "2211.03025_3d74df6beb6fdc6eac844454d295137d": "However, ASR does not have significant gain with UASR, which shows that the PR advantage from UASR may not directly enhance the speech SSL",
        "2211.03025_74a84b04665730ec911506406e1c45a1": "When it comes to understanding tasks (i.e., IC and ST), the one with UASR and PT5 achieves the best performance, demonstrating the semantic benefits introduced by PT5",
        "2211.03025_8d6d4a1f06f2d595a0fd9a9755b5b68f": "Given the wav2vec2, UASR, and PT5 do not update their parameters, we could infer that the UASR as a connector could mitigate the modalities mismatch issue discussed in Sec.",
        "2211.03025_faa108a5ea05e543101ef45bc5196d9e": "Last, it is reasonable that UASR and PT5 cannot improve the performances of speaker identification, as their features barely contain speaker-related information at the design level",
        "2211.03025_51c45b795d5d18a3e4e0c37e8b20a141": "Table",
        "2211.03025_f959646e48c55bc33dba0ef9c75fe8dd": "shows the results in the fine-tuning setting",
        "2211.03025_ebc3f93ca972fe597c7cb2a8a06b25fe": "For all the selected tasks,",
        "2211.03025_2c4669d2aa39ee8ae7054332c2a0350e": "achieves the best performance by using UASR as a connector",
        "2211.03025_4aa660f549796c7bfe8eba499579e3bf": "When applying K-means as a connector (i.e.,",
        "2211.03025_29d819a16313064eaa1a55962443dd07": "), we find similar performance improvements in all four tasks as",
        "2211.03025_78dc7eca4cfe58db184909227bcdab99": "However, with UASR as a connector, the improvements are even larger",
        "2211.03025_98952522814bee01299226539bb41255": "As in the ablation study shown in Table",
        "2211.03025_1ddbd14796b433653d653b271a65210d": ", the one with PT5",
        "2211.03025_fc8b1b01c61f9ca27adf1eb6dcfe4874": "(i.e.,",
        "2211.03025_9cae17b15e1f0cd71e53f7853175a98b": ") reaches the best performance for IC, SF, and ER, while the one with TT5",
        "2211.03025_9069986d050f909bcaa3ecfed6ae8fb9": ") has the best performance for ST",
        "2211.03025_b7b6fb72870182e805c60473b4f765a3": "Based on the experimental results, we would argue that there is a balance between modalities matching and textual semantics.",
        "2211.03025_d5105928da46b8c6286c99db5a43e215": "As for text generation tasks,",
        "2211.03025_9368ec93ba6ada39b388042ecb2d5873": "has better results",
        "2211.03025_5482ec8dcacc2263903a2bc724888192": "shows our proposed method on SQA",
        "2211.03025_83e14a03220525e08ef768c660049d0c": "We only conduct the model with textual pre-trained models, as we find the text information is essential to train the model",
        "2211.03025_06c818582d466ef2397b4ddd206da91d": "For example, model",
        "2211.03025_6d7fdb40605166256a2686ff74065726": "can hardly converge for the task, resulting in 0.0 scores for the test sets",
        "2211.03025_afdcaaf7b6105c549619c0b72ecd60de": "On the contrary, the model",
        "2211.03025_52d1c515a9f02f588383a803f2ef8aaa": "with matched modalities has shown outstanding performances, significantly better than the model",
        "2211.03025_ef8ba13e0db23b00d306d99407202349": "and the best model in",
        "2211.03025_6f8b794f3246b0c1e1780bb4d4d5dc53": "Conclusion",
        "2211.03025_a55d99f01fbfbc693349408bffb6838f": "Though pre-trained models in speech and languages have shown to be effective, it is difficult to sequentially apply speech and language pre-trained models to scenarios of spoken language understanding",
        "2211.03025_4985e7eda458d73bfcc9093ce30b93dc": "In this work, we propose using unsupervised mapping (i.e., UASR in our case) to mitigate the mismatch between modalities",
        "2211.03025_64fc8a984849ec3083bb792590980438": "We first show that adding UASR could enhance the original speech pre-trained model, then UASR is applied as a connector between speech and textual pre-trained models",
        "2211.03025_7b6e2086d1541a8113e72a0db4b0e067": "Extensive experiments, in various tasks and settings, demonstrate the effectiveness of our proposed method, which also shows possible solutions to other scenarios other than speech and language."
    },
    "hierarchy": {
        "1": {
            "2211.03025_e353dbe42c8654f33588d4da0b517469": "2211.03025_520a01a4c82a2a4ffe9a199156f237e6",
            "2211.03025_0b2267c15c76fe3f56448144f4e89922": "2211.03025_e353dbe42c8654f33588d4da0b517469",
            "2211.03025_bb3fe0ef1ead58fb433a57b4d7467fb7": "2211.03025_e353dbe42c8654f33588d4da0b517469",
            "2211.03025_66b4bf4f1f2ef3797f2e51f5cd18d363": "2211.03025_e353dbe42c8654f33588d4da0b517469",
            "2211.03025_fd83a41f0483513ea59fddf3762f29e7": "2211.03025_e353dbe42c8654f33588d4da0b517469",
            "2211.03025_ae78df3eb42e51b7048ee4e0cf4287bc": "2211.03025_e353dbe42c8654f33588d4da0b517469",
            "2211.03025_51f83ff8da94894d5a52e5a15154180b": "2211.03025_e353dbe42c8654f33588d4da0b517469",
            "2211.03025_083724c3d1345c0586856578db3abc65": "2211.03025_e353dbe42c8654f33588d4da0b517469",
            "2211.03025_7758b999ea3565189455f529d5e45afe": "2211.03025_e353dbe42c8654f33588d4da0b517469",
            "2211.03025_cdfa14b00deb1e3fbf8f42e1cfb6d8ef": "2211.03025_e353dbe42c8654f33588d4da0b517469",
            "2211.03025_0b79795d3efc95b9976c7c5b933afce2": "2211.03025_e353dbe42c8654f33588d4da0b517469",
            "2211.03025_4d74542611769bd6f0bc9619fa7ce75a": "2211.03025_0b79795d3efc95b9976c7c5b933afce2",
            "2211.03025_7db06adccab50d2d9fef2888c081f4cd": "2211.03025_0b79795d3efc95b9976c7c5b933afce2",
            "2211.03025_508c81c056c3be8c714aaf691da6d4e3": "2211.03025_0b79795d3efc95b9976c7c5b933afce2",
            "2211.03025_67ba9e1b3b67ff094c5442ebdcad7fc2": "2211.03025_0b79795d3efc95b9976c7c5b933afce2",
            "2211.03025_b126aa7a50ebe19e66d33e94ab2d5334": "2211.03025_0b79795d3efc95b9976c7c5b933afce2",
            "2211.03025_4e4c71de09a8624c5df9a2dda7446ca1": "2211.03025_aa66d95e83ccb800b2bfb705185b36ba",
            "2211.03025_36bc53ee58859ab40e4ba1fc9c47fa8a": "2211.03025_0b79795d3efc95b9976c7c5b933afce2",
            "2211.03025_fb38b379c99db5b214b18fc15b20fc65": "2211.03025_0b79795d3efc95b9976c7c5b933afce2",
            "2211.03025_4bd7889d3fb9921878755ea7f8714e0d": "2211.03025_0b79795d3efc95b9976c7c5b933afce2",
            "2211.03025_209684d705f4718324022e35d1b7b995": "2211.03025_0b79795d3efc95b9976c7c5b933afce2",
            "2211.03025_1969acd3dc4d0c224f2e6fcf6cfe6805": "2211.03025_0b79795d3efc95b9976c7c5b933afce2",
            "2211.03025_bea882746951b8b823700f58468dd879": "2211.03025_0b79795d3efc95b9976c7c5b933afce2",
            "2211.03025_eeea279c53f15f885b45cd548c31e75e": "2211.03025_0b79795d3efc95b9976c7c5b933afce2",
            "2211.03025_f1b253b315fd75072f3220c2b89308eb": "2211.03025_0b79795d3efc95b9976c7c5b933afce2",
            "2211.03025_ef3a52dc222abe39455c4540cbd0453e": "2211.03025_922201349a90c140e102732097e41d13",
            "2211.03025_3278ae53b63f2538160c88f3356b2c01": "2211.03025_0b79795d3efc95b9976c7c5b933afce2",
            "2211.03025_a32b3b51ba2ecf1ada69790143464301": "2211.03025_0b79795d3efc95b9976c7c5b933afce2",
            "2211.03025_50315cbce8137261e37f44ac3a27cc3c": "2211.03025_0b79795d3efc95b9976c7c5b933afce2",
            "2211.03025_91d460c24a1561aaa43d9ce131e94214": "2211.03025_0b79795d3efc95b9976c7c5b933afce2",
            "2211.03025_59fb84f021b0645c204a8113ae1a1c2c": "2211.03025_0b79795d3efc95b9976c7c5b933afce2",
            "2211.03025_abf4e379e939031a3f3c716d3cd62c03": "2211.03025_0b79795d3efc95b9976c7c5b933afce2",
            "2211.03025_2d4cb2da16553cc035889a5859913d6e": "2211.03025_0b79795d3efc95b9976c7c5b933afce2",
            "2211.03025_06d9ef9e46ebb6ec14a4bfdfbc96147e": "2211.03025_0b79795d3efc95b9976c7c5b933afce2",
            "2211.03025_a060b1836299e2675f6ec8a6b1a58826": "2211.03025_0b79795d3efc95b9976c7c5b933afce2",
            "2211.03025_5af78326f60014ae942f3f31c428765d": "2211.03025_0b79795d3efc95b9976c7c5b933afce2",
            "2211.03025_c8d830c51b9eacd001e0681d40011133": "2211.03025_0b79795d3efc95b9976c7c5b933afce2",
            "2211.03025_fd6383547091313ad3d58d14a81c16b0": "2211.03025_0b79795d3efc95b9976c7c5b933afce2",
            "2211.03025_cb0ebf90a8d915c06f9e5aa93eb1914b": "2211.03025_0b79795d3efc95b9976c7c5b933afce2",
            "2211.03025_0f88f0a2c86db0f8f5f9cc2539b21a12": "2211.03025_d1fb541327a140ceab489f7029524517",
            "2211.03025_8c646394c4addfac3b7698622c8ddcc7": "2211.03025_0b79795d3efc95b9976c7c5b933afce2",
            "2211.03025_b72350a1d64957d88ff5e944bc53e90d": "2211.03025_0b79795d3efc95b9976c7c5b933afce2",
            "2211.03025_eea7da2d8bfa7985b255b0d9855aab42": "2211.03025_0b79795d3efc95b9976c7c5b933afce2",
            "2211.03025_ddaa20befe1a3c147ff2ee52314a87fb": "2211.03025_0b79795d3efc95b9976c7c5b933afce2",
            "2211.03025_ce2533ade5cc97dcc765a113ae938bab": "2211.03025_0b79795d3efc95b9976c7c5b933afce2",
            "2211.03025_465eab9b55099c06e55098ef683be074": "2211.03025_0b79795d3efc95b9976c7c5b933afce2",
            "2211.03025_332e874cb2c5d1813da68301f442ce79": "2211.03025_0b79795d3efc95b9976c7c5b933afce2",
            "2211.03025_a141bc16469b30f2722916d1becccff2": "2211.03025_aa66d95e83ccb800b2bfb705185b36ba",
            "2211.03025_78195af496c101e8ae672e98f1e3399f": "2211.03025_0b79795d3efc95b9976c7c5b933afce2",
            "2211.03025_cceefdba8abd770753c308b997d45982": "2211.03025_aa66d95e83ccb800b2bfb705185b36ba",
            "2211.03025_b638b5aa5f4c5950fba110ec00417ac4": "2211.03025_0b79795d3efc95b9976c7c5b933afce2",
            "2211.03025_4e7f790cb183486c92aaceaa108aa9f3": "2211.03025_aa66d95e83ccb800b2bfb705185b36ba",
            "2211.03025_5300f8543d205fa32af100bdc290a0b4": "2211.03025_0b79795d3efc95b9976c7c5b933afce2",
            "2211.03025_8c012419dbbed17f23d760adf36ce7f5": "2211.03025_0b79795d3efc95b9976c7c5b933afce2",
            "2211.03025_5058f1af8388633f609cadb75a75dc9d": "2211.03025_d1fb541327a140ceab489f7029524517",
            "2211.03025_1b8beac96733a54f513a835e96a9b592": "2211.03025_0b79795d3efc95b9976c7c5b933afce2",
            "2211.03025_2ba0c1d2f0f117d4512ef6170fe0e015": "2211.03025_e353dbe42c8654f33588d4da0b517469",
            "2211.03025_a9ded1e5ce5d75814730bb4caaf49419": "2211.03025_2ba0c1d2f0f117d4512ef6170fe0e015",
            "2211.03025_3cbad4d8989ae42c78fb1c2d525776b9": "2211.03025_a9ded1e5ce5d75814730bb4caaf49419",
            "2211.03025_d32d37913d080c820cc49bc5f36ab5b5": "2211.03025_a9ded1e5ce5d75814730bb4caaf49419",
            "2211.03025_e559a39d7e0ba7d9b7991ab897d32ea8": "2211.03025_aa66d95e83ccb800b2bfb705185b36ba",
            "2211.03025_6496af9c5798195c1b3e753f909239dd": "2211.03025_a9ded1e5ce5d75814730bb4caaf49419",
            "2211.03025_8824595f458085fe3bf467c4228300fc": "2211.03025_a9ded1e5ce5d75814730bb4caaf49419",
            "2211.03025_595ee636d53856b548c13644b99c740c": "2211.03025_a9ded1e5ce5d75814730bb4caaf49419",
            "2211.03025_71e97de845ac1655be37cec2c5b12014": "2211.03025_a9ded1e5ce5d75814730bb4caaf49419",
            "2211.03025_7827a02c3d1561a1d013597e35566cbb": "2211.03025_9399c1fce9154541c6ee71269a9a84e2",
            "2211.03025_5da7171ed0788cbeeae52a7d894a56bb": "2211.03025_a9ded1e5ce5d75814730bb4caaf49419",
            "2211.03025_5a6c093b5f54ca0974067982efc8f2b7": "2211.03025_a9ded1e5ce5d75814730bb4caaf49419",
            "2211.03025_333bd489f2aefb7c519a7e3da2fa8378": "2211.03025_a9ded1e5ce5d75814730bb4caaf49419",
            "2211.03025_a29f17caa3e965b909d1aef183a202e4": "2211.03025_a9ded1e5ce5d75814730bb4caaf49419",
            "2211.03025_2f118ee06d05f3c2d98361d9c30e38ce": "2211.03025_a9ded1e5ce5d75814730bb4caaf49419",
            "2211.03025_6b4effe9641010fbf752796449447d11": "2211.03025_a9ded1e5ce5d75814730bb4caaf49419",
            "2211.03025_51d57b0acdbd04299fbe5ad89221b87b": "2211.03025_a9ded1e5ce5d75814730bb4caaf49419",
            "2211.03025_47408740fea5a10fbbd74cd74a5d5382": "2211.03025_a9ded1e5ce5d75814730bb4caaf49419",
            "2211.03025_930b956ef51654e0669455a2cdd62fb5": "2211.03025_1bfe57d150d58583d44df39b0d3484fd",
            "2211.03025_ebadbe0b39b727044142cc825fb02ba7": "2211.03025_a9ded1e5ce5d75814730bb4caaf49419",
            "2211.03025_12b4d20e893dfc5ab03c489b17b0de00": "2211.03025_a9ded1e5ce5d75814730bb4caaf49419",
            "2211.03025_52294f9045816d20191d31186a73dc56": "2211.03025_a9ded1e5ce5d75814730bb4caaf49419",
            "2211.03025_42c7c17c6797093b30665e8aa7dde146": "2211.03025_a9ded1e5ce5d75814730bb4caaf49419",
            "2211.03025_d6bc7c374633434768149e90c7d435ef": "2211.03025_a9ded1e5ce5d75814730bb4caaf49419",
            "2211.03025_22c23dd5bea6a6e01b55a51f9a145b1c": "2211.03025_a9ded1e5ce5d75814730bb4caaf49419",
            "2211.03025_de87b8952c041ad1d74793e86ff6aae8": "2211.03025_a9ded1e5ce5d75814730bb4caaf49419",
            "2211.03025_0c6b436dbc1ba0b8d6a0149471f872b8": "2211.03025_a9ded1e5ce5d75814730bb4caaf49419",
            "2211.03025_dd5bff875ed9ad942ac26dc14decbf8a": "2211.03025_a9ded1e5ce5d75814730bb4caaf49419",
            "2211.03025_a6ba0a5ed91ad0a84b695e8ce84cd356": "2211.03025_a9ded1e5ce5d75814730bb4caaf49419",
            "2211.03025_68a463cbf8842017bbbab8ca879333c7": "2211.03025_a9ded1e5ce5d75814730bb4caaf49419",
            "2211.03025_4c144b6052db6f9b68c8594899c601a2": "2211.03025_a9ded1e5ce5d75814730bb4caaf49419",
            "2211.03025_db5f7b3e9934fbc5a2859d88c4ba84a3": "2211.03025_a9ded1e5ce5d75814730bb4caaf49419",
            "2211.03025_c2566205d713dc99a54018a7870a4b37": "2211.03025_a9ded1e5ce5d75814730bb4caaf49419",
            "2211.03025_e595da9631a2dfb03d0048c6c3bec7ab": "2211.03025_9399c1fce9154541c6ee71269a9a84e2",
            "2211.03025_20db16323e0853a8774699e4b2a63fd2": "2211.03025_a9ded1e5ce5d75814730bb4caaf49419",
            "2211.03025_23f3aecb7fcd139009be9a162be26b77": "2211.03025_9399c1fce9154541c6ee71269a9a84e2",
            "2211.03025_7805c32557871f0c160d2d70a4650761": "2211.03025_a9ded1e5ce5d75814730bb4caaf49419",
            "2211.03025_7c546f380643ec6c63837bd809e73c0e": "2211.03025_aa66d95e83ccb800b2bfb705185b36ba",
            "2211.03025_328c743e0271d85bc3f78557dc18aafd": "2211.03025_a9ded1e5ce5d75814730bb4caaf49419",
            "2211.03025_17f6b595a3b9a0e7c108c5d0c44b6144": "2211.03025_a9ded1e5ce5d75814730bb4caaf49419",
            "2211.03025_054939ab2c639ccb9e596e8a42ca480b": "2211.03025_a9ded1e5ce5d75814730bb4caaf49419",
            "2211.03025_862c67d66ec91c59224efac09221e784": "2211.03025_a9ded1e5ce5d75814730bb4caaf49419",
            "2211.03025_1df51cbd38487f40dae2ffa9c583e9d3": "2211.03025_a9ded1e5ce5d75814730bb4caaf49419",
            "2211.03025_cf84d3bab68d5595c0e61ff25cf682de": "2211.03025_a9ded1e5ce5d75814730bb4caaf49419",
            "2211.03025_9857d9db30074055658db2b7e7c7a8a1": "2211.03025_a9ded1e5ce5d75814730bb4caaf49419",
            "2211.03025_3de71b63340ab8d2524a258abeaba924": "2211.03025_a9ded1e5ce5d75814730bb4caaf49419",
            "2211.03025_ac338cdb8cda0290f8497dfdbcecbda8": "2211.03025_aa66d95e83ccb800b2bfb705185b36ba",
            "2211.03025_9b2d5a803a24aeebc1d84d7a43d66732": "2211.03025_a9ded1e5ce5d75814730bb4caaf49419",
            "2211.03025_ad4c54b864c01957a9f251677c04183e": "2211.03025_a9ded1e5ce5d75814730bb4caaf49419",
            "2211.03025_f19066c1896240f230af541735499450": "2211.03025_a9ded1e5ce5d75814730bb4caaf49419",
            "2211.03025_567904efe9e64d9faf3e41ef402cb568": "2211.03025_1bfe57d150d58583d44df39b0d3484fd",
            "2211.03025_e5552f58c8ed59d7fb70aa9f7c9ec842": "2211.03025_a9ded1e5ce5d75814730bb4caaf49419",
            "2211.03025_292e89dd64d9ca96c35430a04d73c406": "2211.03025_a9ded1e5ce5d75814730bb4caaf49419",
            "2211.03025_89d9ce70a014252e580e2b44a6b68548": "2211.03025_a9ded1e5ce5d75814730bb4caaf49419",
            "2211.03025_21681ccce8d2b68b4707b51b6e9f8ad1": "2211.03025_a9ded1e5ce5d75814730bb4caaf49419",
            "2211.03025_231cb07c56ef0f14d722140514bff617": "2211.03025_a9ded1e5ce5d75814730bb4caaf49419",
            "2211.03025_d3ed97478e5bb62df6a73642fb3eb2cf": "2211.03025_2ba0c1d2f0f117d4512ef6170fe0e015",
            "2211.03025_feaab97b2c4fb80ab18e358659c74198": "2211.03025_d3ed97478e5bb62df6a73642fb3eb2cf",
            "2211.03025_6b579e69678c3cb5c3accfc3c6d3b53e": "2211.03025_d3ed97478e5bb62df6a73642fb3eb2cf",
            "2211.03025_f8eaedfcc2a3e0a6bae899550f75be21": "2211.03025_d3ed97478e5bb62df6a73642fb3eb2cf",
            "2211.03025_0c3996c24241afa482f64e8f9b703e3f": "2211.03025_d3ed97478e5bb62df6a73642fb3eb2cf",
            "2211.03025_426a5ff7c7b14928d60c8adcc9acd973": "2211.03025_d3ed97478e5bb62df6a73642fb3eb2cf",
            "2211.03025_f6413e2673ee0ba35a3e434b2ad51ee5": "2211.03025_1bfe57d150d58583d44df39b0d3484fd",
            "2211.03025_023136296873cecf0eddd3aa7dc567c8": "2211.03025_d3ed97478e5bb62df6a73642fb3eb2cf",
            "2211.03025_93890d00a22bc16357299f69868b0201": "2211.03025_d3ed97478e5bb62df6a73642fb3eb2cf",
            "2211.03025_95939da53aaf9cab5af3a5d7c6fb4fc5": "2211.03025_d3ed97478e5bb62df6a73642fb3eb2cf",
            "2211.03025_7aefcecda73e6969b672941164d51045": "2211.03025_d3ed97478e5bb62df6a73642fb3eb2cf",
            "2211.03025_f828277b9b63a7409a02b5bd2168ae5b": "2211.03025_d3ed97478e5bb62df6a73642fb3eb2cf",
            "2211.03025_7c033aa21e8a2232531a74f4889b430b": "2211.03025_d3ed97478e5bb62df6a73642fb3eb2cf",
            "2211.03025_be2081ca85be8b98895b43eb5838f000": "2211.03025_d3ed97478e5bb62df6a73642fb3eb2cf",
            "2211.03025_9399c1fce9154541c6ee71269a9a84e2": "2211.03025_2ba0c1d2f0f117d4512ef6170fe0e015",
            "2211.03025_37b0abd9c22d3502f98869b0f707743d": "2211.03025_9399c1fce9154541c6ee71269a9a84e2",
            "2211.03025_0f08f6b38cf5e59043e7db5500377b64": "2211.03025_9399c1fce9154541c6ee71269a9a84e2",
            "2211.03025_48f6e9e2f826b98566db5598211af8c3": "2211.03025_9399c1fce9154541c6ee71269a9a84e2",
            "2211.03025_be5d5d37542d75f93a87094459f76678": "2211.03025_1bfe57d150d58583d44df39b0d3484fd",
            "2211.03025_196c6e818eee01dbe7b3781f06193b95": "2211.03025_aa66d95e83ccb800b2bfb705185b36ba",
            "2211.03025_155f724954564cb756f588edf75d3a52": "2211.03025_9399c1fce9154541c6ee71269a9a84e2",
            "2211.03025_b62096207b380e041aa4b47046c7ed0d": "2211.03025_9399c1fce9154541c6ee71269a9a84e2",
            "2211.03025_99d4492cfc8bdc7e35891aaf418b1a7f": "2211.03025_9399c1fce9154541c6ee71269a9a84e2",
            "2211.03025_cfdc86c5ef23e313d05311fa27953cb1": "2211.03025_9399c1fce9154541c6ee71269a9a84e2",
            "2211.03025_76501284e0ea655d387f82a6a754b033": "2211.03025_9399c1fce9154541c6ee71269a9a84e2",
            "2211.03025_5474d5ad49d775d5be6b38407d20875f": "2211.03025_9399c1fce9154541c6ee71269a9a84e2",
            "2211.03025_eb8640cc4cd425198a4f92ac132a5bcc": "2211.03025_9399c1fce9154541c6ee71269a9a84e2",
            "2211.03025_0f51e5a000bfc7b6ec6e45fa2083027b": "2211.03025_9399c1fce9154541c6ee71269a9a84e2",
            "2211.03025_0ccfe5be0b16474da2ea438d0c6a919c": "2211.03025_9399c1fce9154541c6ee71269a9a84e2",
            "2211.03025_df5e76fc6e0cf33469544ef57ad8cd17": "2211.03025_9399c1fce9154541c6ee71269a9a84e2",
            "2211.03025_165e486f50318efb515f944aa5dfeac8": "2211.03025_9399c1fce9154541c6ee71269a9a84e2",
            "2211.03025_c8c3f73414972cc72adc3b88c7e0422c": "2211.03025_9399c1fce9154541c6ee71269a9a84e2",
            "2211.03025_6b6683ba13edc01e91ac4fa76ac8c53a": "2211.03025_9399c1fce9154541c6ee71269a9a84e2",
            "2211.03025_9774c2b89829a0e743a20daf2fa62b26": "2211.03025_9399c1fce9154541c6ee71269a9a84e2",
            "2211.03025_a4704fd35f0308287f2937ba3eccf5fe": "2211.03025_9399c1fce9154541c6ee71269a9a84e2",
            "2211.03025_3bcc2fd71ef0935e43b2ef346fe8f824": "2211.03025_9399c1fce9154541c6ee71269a9a84e2",
            "2211.03025_4f2d1fae77331b81f0a21f8185ec19f1": "2211.03025_9399c1fce9154541c6ee71269a9a84e2",
            "2211.03025_1bfe57d150d58583d44df39b0d3484fd": "2211.03025_2ba0c1d2f0f117d4512ef6170fe0e015",
            "2211.03025_4cd28de907145bc8e6813ae81fa0c3da": "2211.03025_aa66d95e83ccb800b2bfb705185b36ba",
            "2211.03025_c05090f0a8707f8582b0e854f072af5b": "2211.03025_1bfe57d150d58583d44df39b0d3484fd",
            "2211.03025_ebd5adeb2dc306dab15632b544cdf20b": "2211.03025_1bfe57d150d58583d44df39b0d3484fd",
            "2211.03025_d5bd9e710f8deeb124e502cc3de8166d": "2211.03025_1bfe57d150d58583d44df39b0d3484fd",
            "2211.03025_ca0a0c8e7708773e0e70a708c55adb57": "2211.03025_1bfe57d150d58583d44df39b0d3484fd",
            "2211.03025_4ae3450930a4c2e3dbfe890ce236428a": "2211.03025_1bfe57d150d58583d44df39b0d3484fd",
            "2211.03025_7109f6dd942cf26d288485503650cff2": "2211.03025_1bfe57d150d58583d44df39b0d3484fd",
            "2211.03025_a8c34cffa0ed573d43de5c6d85834dd0": "2211.03025_1bfe57d150d58583d44df39b0d3484fd",
            "2211.03025_d90030ee6001ab2df3cc487a6fffd614": "2211.03025_1bfe57d150d58583d44df39b0d3484fd",
            "2211.03025_c7fb5eb468af5eed821d084d9c9b08cf": "2211.03025_1bfe57d150d58583d44df39b0d3484fd",
            "2211.03025_188352b463d4f7a5afa3ce7b2a444be2": "2211.03025_1bfe57d150d58583d44df39b0d3484fd",
            "2211.03025_76c9602559465fb10e8ffbb598bd9369": "2211.03025_1bfe57d150d58583d44df39b0d3484fd",
            "2211.03025_75b070d32e416f57cb438eda74054dfc": "2211.03025_1bfe57d150d58583d44df39b0d3484fd",
            "2211.03025_2756d240dd4ae4350bb92e09ce95797f": "2211.03025_1bfe57d150d58583d44df39b0d3484fd",
            "2211.03025_d67356b045763f57785a89f84ce546a0": "2211.03025_1bfe57d150d58583d44df39b0d3484fd",
            "2211.03025_17349b18ec9ea5c2d535a362a2d820b7": "2211.03025_1bfe57d150d58583d44df39b0d3484fd",
            "2211.03025_a3b0261e195fb9d8220cacd961e504d5": "2211.03025_1bfe57d150d58583d44df39b0d3484fd",
            "2211.03025_eb13a88d27918037558fd3450df3e83a": "2211.03025_1bfe57d150d58583d44df39b0d3484fd",
            "2211.03025_2bb612101cc607107d95e3e908c646fc": "2211.03025_1bfe57d150d58583d44df39b0d3484fd",
            "2211.03025_7651ba0e8e29ee7537841a819041a172": "2211.03025_1bfe57d150d58583d44df39b0d3484fd",
            "2211.03025_672db0d1623dbd241d611c9a035e1d30": "2211.03025_1bfe57d150d58583d44df39b0d3484fd",
            "2211.03025_ea771a7a932d5ac625002df279bc0697": "2211.03025_1bfe57d150d58583d44df39b0d3484fd",
            "2211.03025_cc6a176bc80fdf292f529b18ebcbe37d": "2211.03025_1bfe57d150d58583d44df39b0d3484fd",
            "2211.03025_fda096f64bb07f248cc6d94ce9915a6f": "2211.03025_1bfe57d150d58583d44df39b0d3484fd",
            "2211.03025_438b3d81c28c5f9696d706c8fa09d123": "2211.03025_1bfe57d150d58583d44df39b0d3484fd",
            "2211.03025_3834d9c55f761f7ceab4df37877d360a": "2211.03025_1bfe57d150d58583d44df39b0d3484fd",
            "2211.03025_b9e719677b042dba85d7e2e45cd3388c": "2211.03025_1bfe57d150d58583d44df39b0d3484fd",
            "2211.03025_fd1fb494271c872ca6b688dd1a49ede0": "2211.03025_1bfe57d150d58583d44df39b0d3484fd",
            "2211.03025_4829262cecb9828817b33e0f9c907f91": "2211.03025_e353dbe42c8654f33588d4da0b517469",
            "2211.03025_922201349a90c140e102732097e41d13": "2211.03025_4829262cecb9828817b33e0f9c907f91",
            "2211.03025_af84a1e77c29797293ede9bf9eeaf54f": "2211.03025_922201349a90c140e102732097e41d13",
            "2211.03025_6218d54009e3d39cc5f643e6c048710d": "2211.03025_922201349a90c140e102732097e41d13",
            "2211.03025_72f36ac0a79c56bde7f577638b15caba": "2211.03025_922201349a90c140e102732097e41d13",
            "2211.03025_dedfaabb4af3ea29306614b1b603b6f9": "2211.03025_922201349a90c140e102732097e41d13",
            "2211.03025_8ec5e26b3a21b7b765ad095bdc1215c9": "2211.03025_922201349a90c140e102732097e41d13",
            "2211.03025_c9fc211abade3c4a3b0a0ff5595570a8": "2211.03025_922201349a90c140e102732097e41d13",
            "2211.03025_5b3085e6f5165f6e18fd0fe5d2dbf2a1": "2211.03025_922201349a90c140e102732097e41d13",
            "2211.03025_8f65a23d21470deea698e691b5f02b1d": "2211.03025_922201349a90c140e102732097e41d13",
            "2211.03025_7ace5b856c26e5138bab1ffc93278cc8": "2211.03025_922201349a90c140e102732097e41d13",
            "2211.03025_8c897252df5626bda41a746b844e950f": "2211.03025_922201349a90c140e102732097e41d13",
            "2211.03025_a0d6279bc973a925989993aad6923b7f": "2211.03025_922201349a90c140e102732097e41d13",
            "2211.03025_39ec6aa0554a10e8cb05358ed6a5e2b6": "2211.03025_922201349a90c140e102732097e41d13",
            "2211.03025_37a2bdb177d94c763867a4bdd9fff514": "2211.03025_922201349a90c140e102732097e41d13",
            "2211.03025_a09931985321aff7da3db2091aaad555": "2211.03025_922201349a90c140e102732097e41d13",
            "2211.03025_6ced65face999e4e780c73e30eaaef9d": "2211.03025_922201349a90c140e102732097e41d13",
            "2211.03025_682277f298a9895b785425539b58cf55": "2211.03025_922201349a90c140e102732097e41d13",
            "2211.03025_4140f54cd025a787f4e44471e20ec7ac": "2211.03025_922201349a90c140e102732097e41d13",
            "2211.03025_5750b6ade0af6eb323017c2279decf57": "2211.03025_922201349a90c140e102732097e41d13",
            "2211.03025_5140851000a25500a15df9c475e9db5f": "2211.03025_922201349a90c140e102732097e41d13",
            "2211.03025_7c806f16cf09e3ab91b1e54ce2be2a45": "2211.03025_922201349a90c140e102732097e41d13",
            "2211.03025_0997f670eeaa7063402cf66d9bc0baf7": "2211.03025_922201349a90c140e102732097e41d13",
            "2211.03025_52875b20f38067e5a00658156a03bb1b": "2211.03025_922201349a90c140e102732097e41d13",
            "2211.03025_60fd1e3b3efe81626ded96c2b16a4eba": "2211.03025_922201349a90c140e102732097e41d13",
            "2211.03025_d9adcbe1db8236a99f20c7ea3116aef7": "2211.03025_922201349a90c140e102732097e41d13",
            "2211.03025_01edf4d371afbc4c9844b3dd184997fa": "2211.03025_922201349a90c140e102732097e41d13",
            "2211.03025_5d4aa5e42b9d7396cc1e8d481a326892": "2211.03025_922201349a90c140e102732097e41d13",
            "2211.03025_2407051aab75cf3f178323fc0762dd05": "2211.03025_922201349a90c140e102732097e41d13",
            "2211.03025_220ed546e827681fb04afb62724dc42d": "2211.03025_922201349a90c140e102732097e41d13",
            "2211.03025_1183f006cafff6b8a90c57df1d15c2ab": "2211.03025_922201349a90c140e102732097e41d13",
            "2211.03025_aa66d95e83ccb800b2bfb705185b36ba": "2211.03025_4829262cecb9828817b33e0f9c907f91",
            "2211.03025_efca547ae6f37daf101e0132704e38bc": "2211.03025_aa66d95e83ccb800b2bfb705185b36ba",
            "2211.03025_ee0a82aa5c80341ec6d47db4ba8010e2": "2211.03025_aa66d95e83ccb800b2bfb705185b36ba",
            "2211.03025_333ec17e45dd98d91d1e7e4833523a57": "2211.03025_aa66d95e83ccb800b2bfb705185b36ba",
            "2211.03025_3c8fa38dafcca67310cfbf9c8763b92e": "2211.03025_aa66d95e83ccb800b2bfb705185b36ba",
            "2211.03025_cf67f3dd31df9b70e630ff9aa141c737": "2211.03025_aa66d95e83ccb800b2bfb705185b36ba",
            "2211.03025_4a5ec10fe5f483e25a00f8637d2f1b3c": "2211.03025_aa66d95e83ccb800b2bfb705185b36ba",
            "2211.03025_c94c984707985cdcb0c68c3210f8eef4": "2211.03025_aa66d95e83ccb800b2bfb705185b36ba",
            "2211.03025_7f6d59c971660980539b871320b8f6b4": "2211.03025_aa66d95e83ccb800b2bfb705185b36ba",
            "2211.03025_ccd5ad35e5bc991b7929b8da39b2b436": "2211.03025_aa66d95e83ccb800b2bfb705185b36ba",
            "2211.03025_853ae90f0351324bd73ea615e6487517": "2211.03025_aa66d95e83ccb800b2bfb705185b36ba",
            "2211.03025_15aae9b196cda6e26bf6918fb7088b35": "2211.03025_aa66d95e83ccb800b2bfb705185b36ba",
            "2211.03025_f7faef88bbd01e98e96ccf843ac801fd": "2211.03025_aa66d95e83ccb800b2bfb705185b36ba",
            "2211.03025_59e82251963ab1bedbcc5b96b11727f7": "2211.03025_aa66d95e83ccb800b2bfb705185b36ba",
            "2211.03025_5044dcb2183f819c317da3144eb0c0b7": "2211.03025_aa66d95e83ccb800b2bfb705185b36ba",
            "2211.03025_1be7ec2262294de083755bfcb4dbd4ec": "2211.03025_aa66d95e83ccb800b2bfb705185b36ba",
            "2211.03025_ede23817aed72e76514ac06d5821c518": "2211.03025_aa66d95e83ccb800b2bfb705185b36ba",
            "2211.03025_07ee8ced392b391a8fb012e2fb3a81c0": "2211.03025_aa66d95e83ccb800b2bfb705185b36ba",
            "2211.03025_4e27870fa687da766a9b9ee403acf5db": "2211.03025_aa66d95e83ccb800b2bfb705185b36ba",
            "2211.03025_3f75bc3249ac5ae2c65b6710c749d994": "2211.03025_aa66d95e83ccb800b2bfb705185b36ba",
            "2211.03025_462a115a40954ff90a63325a3793aba3": "2211.03025_aa66d95e83ccb800b2bfb705185b36ba",
            "2211.03025_a42dd9bf321b2b5e1916fd0b3c11fdad": "2211.03025_aa66d95e83ccb800b2bfb705185b36ba",
            "2211.03025_a2f0f116006df7998af93f95d5c9e75f": "2211.03025_aa66d95e83ccb800b2bfb705185b36ba",
            "2211.03025_9eecb7db59d16c80417c72d1e1f4fbf1": "2211.03025_aa66d95e83ccb800b2bfb705185b36ba",
            "2211.03025_9922b6de8634429dab0c676cbe07b541": "2211.03025_aa66d95e83ccb800b2bfb705185b36ba",
            "2211.03025_00d1fea29a3a04973e9d419d20b6e397": "2211.03025_aa66d95e83ccb800b2bfb705185b36ba",
            "2211.03025_adcc7208eaf57b3eb032cae66ef54ca9": "2211.03025_aa66d95e83ccb800b2bfb705185b36ba",
            "2211.03025_2a333e3963fa923448b3105bb9c33eb1": "2211.03025_aa66d95e83ccb800b2bfb705185b36ba",
            "2211.03025_c78a5e06c1dba9ccb975a6deca8ad694": "2211.03025_aa66d95e83ccb800b2bfb705185b36ba",
            "2211.03025_65ac574a52781cbe53689e3f1fa434f9": "2211.03025_aa66d95e83ccb800b2bfb705185b36ba",
            "2211.03025_3f8db846a2ca9a285287b9e8a1b27d63": "2211.03025_aa66d95e83ccb800b2bfb705185b36ba",
            "2211.03025_bed41888aee98a7d4bbfc7c2a3f7635e": "2211.03025_aa66d95e83ccb800b2bfb705185b36ba",
            "2211.03025_52c8c127546e12a412a4085a4157b6f6": "2211.03025_aa66d95e83ccb800b2bfb705185b36ba",
            "2211.03025_9fdf8dfdfe6f825290c347f1427e4d3e": "2211.03025_aa66d95e83ccb800b2bfb705185b36ba",
            "2211.03025_c0cb5f0fcf239ab3d9c1fcd31fff1efc": "2211.03025_aa66d95e83ccb800b2bfb705185b36ba",
            "2211.03025_8a0e2b549d223aba55a866c38d1c9275": "2211.03025_aa66d95e83ccb800b2bfb705185b36ba",
            "2211.03025_ce96ce64475d88003b81a20710c10f5e": "2211.03025_aa66d95e83ccb800b2bfb705185b36ba",
            "2211.03025_ceaa47905061f4fc935944adf7be5259": "2211.03025_aa66d95e83ccb800b2bfb705185b36ba",
            "2211.03025_7c113a786c424a332894c4dcee8a3175": "2211.03025_aa66d95e83ccb800b2bfb705185b36ba",
            "2211.03025_a393ccd9d8ad15576fea621d54a94c68": "2211.03025_aa66d95e83ccb800b2bfb705185b36ba",
            "2211.03025_4c25e524368cf170f8e186db49edd99f": "2211.03025_aa66d95e83ccb800b2bfb705185b36ba",
            "2211.03025_3572cf68da300728b81668b0d535b6d9": "2211.03025_aa66d95e83ccb800b2bfb705185b36ba",
            "2211.03025_7c69097a8648781a3392ee86581e7ec3": "2211.03025_aa66d95e83ccb800b2bfb705185b36ba",
            "2211.03025_dd4e7080cb6874d6ecbc33d7fa70851d": "2211.03025_aa66d95e83ccb800b2bfb705185b36ba",
            "2211.03025_a17607ec8e64ef3579f5f7c6acf7d024": "2211.03025_aa66d95e83ccb800b2bfb705185b36ba",
            "2211.03025_c6aa19525a1453fc7104cba718678010": "2211.03025_aa66d95e83ccb800b2bfb705185b36ba",
            "2211.03025_be16c83bf9c80b906bbc922f03123e35": "2211.03025_aa66d95e83ccb800b2bfb705185b36ba",
            "2211.03025_e31e7718eddd1ccd489dd915988a97b4": "2211.03025_aa66d95e83ccb800b2bfb705185b36ba",
            "2211.03025_43f06d52bd845e4af5b92eb6b88162e2": "2211.03025_aa66d95e83ccb800b2bfb705185b36ba",
            "2211.03025_02c301391bfa1277d05349f7c25cc8cd": "2211.03025_aa66d95e83ccb800b2bfb705185b36ba",
            "2211.03025_25bf66b584fd13c853fea7b7e9357bc1": "2211.03025_aa66d95e83ccb800b2bfb705185b36ba",
            "2211.03025_b9d47e954de1d1c8838ff9c95f997e86": "2211.03025_aa66d95e83ccb800b2bfb705185b36ba",
            "2211.03025_d9bdd8ec3b2a11e65e836c5435f2a3d9": "2211.03025_aa66d95e83ccb800b2bfb705185b36ba",
            "2211.03025_5dc25ff40fe4d108efc31c1c4f638f72": "2211.03025_aa66d95e83ccb800b2bfb705185b36ba",
            "2211.03025_c9740d3ffeef0b9935284711abf97091": "2211.03025_aa66d95e83ccb800b2bfb705185b36ba",
            "2211.03025_dbfb2fca53573cf7efa0d48a66bc39ca": "2211.03025_aa66d95e83ccb800b2bfb705185b36ba",
            "2211.03025_f41dac38d74d0d82bbade650db64641e": "2211.03025_aa66d95e83ccb800b2bfb705185b36ba",
            "2211.03025_9ad5f90b39cc648932e7a53df0d84260": "2211.03025_aa66d95e83ccb800b2bfb705185b36ba",
            "2211.03025_ab761150d4033138082fedd51d37dc3b": "2211.03025_aa66d95e83ccb800b2bfb705185b36ba",
            "2211.03025_d1fb541327a140ceab489f7029524517": "2211.03025_4829262cecb9828817b33e0f9c907f91",
            "2211.03025_a8e9871ae39421409854fcb5f8826690": "2211.03025_d1fb541327a140ceab489f7029524517",
            "2211.03025_ae0c54ab92e16dfffe5f04e7b480e7f6": "2211.03025_d1fb541327a140ceab489f7029524517",
            "2211.03025_3d74df6beb6fdc6eac844454d295137d": "2211.03025_d1fb541327a140ceab489f7029524517",
            "2211.03025_74a84b04665730ec911506406e1c45a1": "2211.03025_d1fb541327a140ceab489f7029524517",
            "2211.03025_8d6d4a1f06f2d595a0fd9a9755b5b68f": "2211.03025_d1fb541327a140ceab489f7029524517",
            "2211.03025_faa108a5ea05e543101ef45bc5196d9e": "2211.03025_d1fb541327a140ceab489f7029524517",
            "2211.03025_51c45b795d5d18a3e4e0c37e8b20a141": "2211.03025_d1fb541327a140ceab489f7029524517",
            "2211.03025_f959646e48c55bc33dba0ef9c75fe8dd": "2211.03025_d1fb541327a140ceab489f7029524517",
            "2211.03025_ebc3f93ca972fe597c7cb2a8a06b25fe": "2211.03025_d1fb541327a140ceab489f7029524517",
            "2211.03025_2c4669d2aa39ee8ae7054332c2a0350e": "2211.03025_d1fb541327a140ceab489f7029524517",
            "2211.03025_4aa660f549796c7bfe8eba499579e3bf": "2211.03025_d1fb541327a140ceab489f7029524517",
            "2211.03025_29d819a16313064eaa1a55962443dd07": "2211.03025_d1fb541327a140ceab489f7029524517",
            "2211.03025_78dc7eca4cfe58db184909227bcdab99": "2211.03025_d1fb541327a140ceab489f7029524517",
            "2211.03025_98952522814bee01299226539bb41255": "2211.03025_d1fb541327a140ceab489f7029524517",
            "2211.03025_1ddbd14796b433653d653b271a65210d": "2211.03025_d1fb541327a140ceab489f7029524517",
            "2211.03025_fc8b1b01c61f9ca27adf1eb6dcfe4874": "2211.03025_d1fb541327a140ceab489f7029524517",
            "2211.03025_9cae17b15e1f0cd71e53f7853175a98b": "2211.03025_d1fb541327a140ceab489f7029524517",
            "2211.03025_9069986d050f909bcaa3ecfed6ae8fb9": "2211.03025_d1fb541327a140ceab489f7029524517",
            "2211.03025_b7b6fb72870182e805c60473b4f765a3": "2211.03025_d1fb541327a140ceab489f7029524517",
            "2211.03025_d5105928da46b8c6286c99db5a43e215": "2211.03025_d1fb541327a140ceab489f7029524517",
            "2211.03025_9368ec93ba6ada39b388042ecb2d5873": "2211.03025_d1fb541327a140ceab489f7029524517",
            "2211.03025_5482ec8dcacc2263903a2bc724888192": "2211.03025_d1fb541327a140ceab489f7029524517",
            "2211.03025_83e14a03220525e08ef768c660049d0c": "2211.03025_d1fb541327a140ceab489f7029524517",
            "2211.03025_06c818582d466ef2397b4ddd206da91d": "2211.03025_d1fb541327a140ceab489f7029524517",
            "2211.03025_6d7fdb40605166256a2686ff74065726": "2211.03025_d1fb541327a140ceab489f7029524517",
            "2211.03025_afdcaaf7b6105c549619c0b72ecd60de": "2211.03025_d1fb541327a140ceab489f7029524517",
            "2211.03025_52d1c515a9f02f588383a803f2ef8aaa": "2211.03025_d1fb541327a140ceab489f7029524517",
            "2211.03025_ef8ba13e0db23b00d306d99407202349": "2211.03025_d1fb541327a140ceab489f7029524517",
            "2211.03025_6f8b794f3246b0c1e1780bb4d4d5dc53": "2211.03025_e353dbe42c8654f33588d4da0b517469",
            "2211.03025_a55d99f01fbfbc693349408bffb6838f": "2211.03025_6f8b794f3246b0c1e1780bb4d4d5dc53",
            "2211.03025_4985e7eda458d73bfcc9093ce30b93dc": "2211.03025_6f8b794f3246b0c1e1780bb4d4d5dc53",
            "2211.03025_64fc8a984849ec3083bb792590980438": "2211.03025_6f8b794f3246b0c1e1780bb4d4d5dc53",
            "2211.03025_7b6e2086d1541a8113e72a0db4b0e067": "2211.03025_6f8b794f3246b0c1e1780bb4d4d5dc53"
        }
    }
}